Workbook

Sheet Painel
B2: LINHA EDITORA — Painel de Gestão
B3: Atualiza sozinho a partir das abas. Não digite aqui.
B5: CATÁLOGO | E5: FINANCEIRO
B6: Títulos cadastrados | C6: =COUNTA(Catálogo!A5:A304) -> 2 | E6: Receita de vendas (R$) | F6: =SUM(Vendas!J5:J304) -> 10680
B7: Publicados | C7: =COUNTIF(Catálogo!M5:M304,"Publicado") -> 1 | E7: Exemplares vendidos | F7: =SUM(Vendas!E5:E304) -> 220
B8: Em produção / pré-venda | C8: =COUNTIF(Catálogo!M5:M304,"Em produção")+COUNTIF(Catálogo!M5:M304,"Pré-venda") -> 1 | E8: Total de receitas no caixa (R$) | F8: =SUMIFS(Financeiro!F5:F304,Financeiro!B5:B304,"Receita") -> 5988
B9: Exemplares em estoque | C9: =SUM(Catálogo!O5:O304) -> 1280 | E9: Total de despesas no caixa (R$) | F9: =SUMIFS(Financeiro!F5:F304,Financeiro!B5:B304,"Despesa") -> 6200
B10: Autores ativos | C10: =COUNTA(Autores!A5:A304) -> 2 | E10: Resultado (R$) | F10: =F8-F9 -> -212
B11: Etapas de produção atrasadas | C11: =COUNTIFS(Produção!H5:H304,">0",Produção!G5:G304,"<>Concluído") -> 2 | E11: Royalties a pagar (R$) | F11: =SUM(Autores!L5:L304) -> 798.4
B13: CRM | E13: RECEITA POR CANAL
B14: Contatos ativos | C14: =COUNTIF(CRM_Contatos!K5:K304,"Sim") -> 3 | E14: Site próprio | F14: =SUMIFS(Vendas!$J$5:$J$304,Vendas!$H$5:$H$304,"Site próprio") -> 9582
B15: Oportunidades abertas | C15: =COUNTIFS(CRM_Pipeline!A5:A304,"<>",CRM_Pipeline!E5:E304,"<>Fechado*") -> 2 | E15: Amazon | F15: =SUMIFS(Vendas!$J$5:$J$304,Vendas!$H$5:$H$304,"Amazon") -> 0
B16: Pipeline total (R$) | C16: =SUMIFS(CRM_Pipeline!F5:F304,CRM_Pipeline!E5:E304,"<>Fechado*") -> 9258.2 | E16: Livrarias | F16: =SUMIFS(Vendas!$J$5:$J$304,Vendas!$H$5:$H$304,"Livrarias") -> 0
B17: Pipeline ponderado (R$) | C17: =SUMIFS(CRM_Pipeline!H5:H304,CRM_Pipeline!E5:E304,"<>Fechado*") -> 6629.1 | E17: Distribuidora | F17: =SUMIFS(Vendas!$J$5:$J$304,Vendas!$H$5:$H$304,"Distribuidora") -> 1098
B18: Ações atrasadas | C18: =COUNTIF(CRM_Pipeline!L5:L304,"Atrasada") -> 0 | E18: Feiras/Eventos | F18: =SUMIFS(Vendas!$J$5:$J$304,Vendas!$H$5:$H$304,"Feiras/Eventos") -> 0
B19: Negócios ganhos (R$) | C19: =SUMIFS(CRM_Pipeline!F5:F304,CRM_Pipeline!E5:E304,"Fechado - ganho") -> 0 | E19: Venda direta | F19: =SUMIFS(Vendas!$J$5:$J$304,Vendas!$H$5:$H$304,"Venda direta") -> 0
E20: Governo/Escolas | F20: =SUMIFS(Vendas!$J$5:$J$304,Vendas!$H$5:$H$304,"Governo/Escolas") -> 0
E21: E-book | F21: =SUMIFS(Vendas!$J$5:$J$304,Vendas!$H$5:$H$304,"E-book") -> 0
B23: FUNIL (valor por etapa)
B24: Lead | C24: =SUMIFS(CRM_Pipeline!$F$5:$F$304,CRM_Pipeline!$E$5:$E$304,"Lead") -> 0
B25: Contato feito | C25: =SUMIFS(CRM_Pipeline!$F$5:$F$304,CRM_Pipeline!$E$5:$E$304,"Contato feito") -> 0
B26: Amostra enviada | C26: =SUMIFS(CRM_Pipeline!$F$5:$F$304,CRM_Pipeline!$E$5:$E$304,"Amostra enviada") -> 0
B27: Proposta | C27: =SUMIFS(CRM_Pipeline!$F$5:$F$304,CRM_Pipeline!$E$5:$E$304,"Proposta") -> 1258.2
B28: Negociação | C28: =SUMIFS(CRM_Pipeline!$F$5:$F$304,CRM_Pipeline!$E$5:$E$304,"Negociação") -> 8000
B29: Fechado - ganho | C29: =SUMIFS(CRM_Pipeline!$F$5:$F$304,CRM_Pipeline!$E$5:$E$304,"Fechado - ganho") -> 0
B30: Fechado - perdido | C30: =SUMIFS(CRM_Pipeline!$F$5:$F$304,CRM_Pipeline!$E$5:$E$304,"Fechado - perdido") -> 0

Sheet Como usar
B2: Como usar esta planilha
B4: Legenda
B5: Texto azul | C5: Campo para você preencher.
B6: Texto preto | C6: Fórmula calculada na própria aba — não sobrescreva.
B7: Texto verde | C7: Valor puxado de outra aba (ex.: título a partir do ISBN).
B8: Exemplos | C8: As linhas marcadas com 'Exemplo' mostram o formato esperado. Apague-as quando inserir dados reais.
B10: Fluxo sugerido
B11: 1. Listas | C11: Ajuste os menus suspensos (gêneros, canais, responsáveis, categorias, etapas do funil e probabilidades).
B12: 2. Autores | C12: Cadastre autores e contratos (% de royalties e adiantamento).
B13: 3. Catálogo | C13: Cadastre cada título pelo ISBN — o ISBN é a chave que liga Vendas, Estoque e Royalties.
B14: 4. Produção | C14: Uma linha por etapa de cada livro. Prazos vencidos ficam em vermelho.
B15: 5. CRM_Contatos | C15: Livrarias, distribuidoras, imprensa, influenciadores, escolas. Cada contato recebe um ID (C001, C002…).
B16: 6. CRM_Interações | C16: Registre cada conversa com o ID do contato — 'Última interação' atualiza sozinha.
B17: 7. CRM_Pipeline | C17: Oportunidades de venda B2B. Escolha a etapa do funil: a probabilidade e o valor ponderado são automáticos.
B18: 8. Vendas | C18: Lance cada venda com ISBN, quantidade, preço cobrado e canal. Alimenta estoque, royalties e o Painel.
B19: 9. Financeiro | C19: Todas as entradas e saídas de caixa (gráfica, revisão, marketing, impostos…).
B20: 10. Painel | C20: Visão geral de catálogo, finanças, CRM e funil.
B22: Premissas
B23: Royalties | C23: Calculados sobre o preço de capa × exemplares vendidos (prática comum no Brasil). Adiantamento é abatido.
B24: Probabilidades | C24: Os percentuais do funil (aba Listas) são referências genéricas, não dados da editora — ajuste com o tempo.
B25: Capacidade | C25: As abas estão preparadas com fórmulas para 300 linhas cada.

Sheet Catálogo
A1: Catálogo
A2: Cadastro de todos os títulos. Preencha colunas em azul; colunas em preto são calculadas.
O3: Estoque < 50 fica em vermelho
A4: ISBN | B4: Título | C4: Autor | D4: Gênero | E4: Formato | F4: Páginas | G4: Preço de capa (R$) | H4: Custo unitário (R$) | I4: Margem unitária (R$) | J4: Margem % | K4: Tiragem | L4: Data de lançamento | M4: Status | N4: Vendidos (un.) | O4: Estoque (un.) | P4: Receita líquida (R$) | Q4: Observações
A5: 978-65-00000-01-1 | B5: O Limiar | C5: Ana Exemplo | D5: Romance | E5: Brochura | F5: 240 | G5: 69.9 | H5: 14.5 | I5: =IF(G5="","",G5-H5) -> 55.4 | J5: =IF(OR(G5="",G5=0),"",I5/G5) -> 0.7925608 | K5: 1000 | L5: 46346 | M5: Pré-venda | N5: =IF(A5="","",SUMIFS(Vendas!$E$5:$E$304,Vendas!$B$5:$B$304,A5)) -> 60 | O5: =IF(A5="","",K5-N5) -> 940 | P5: =IF(A5="","",SUMIFS(Vendas!$J$5:$J$304,Vendas!$B$5:$B$304,A5)) -> 3594 | Q5: Exemplo — substitua
A6: 978-65-00000-02-8 | B6: Cartas ao Mar | C6: Bruno Exemplo | D6: Poesia | E6: Brochura | F6: 112 | G6: 49.9 | H6: 9.8 | I6: =IF(G6="","",G6-H6) -> 40.1 | J6: =IF(OR(G6="",G6=0),"",I6/G6) -> 0.80360721 | K6: 500 | L6: 46239 | M6: Publicado | N6: =IF(A6="","",SUMIFS(Vendas!$E$5:$E$304,Vendas!$B$5:$B$304,A6)) -> 160 | O6: =IF(A6="","",K6-N6) -> 340 | P6: =IF(A6="","",SUMIFS(Vendas!$J$5:$J$304,Vendas!$B$5:$B$304,A6)) -> 7086 | Q6: Exemplo — substitua
I7: =IF(G7="","",G7-H7) | J7: =IF(OR(G7="",G7=0),"",I7/G7) | N7: =IF(A7="","",SUMIFS(Vendas!$E$5:$E$304,Vendas!$B$5:$B$304,A7)) | O7: =IF(A7="","",K7-N7) | P7: =IF(A7="","",SUMIFS(Vendas!$J$5:$J$304,Vendas!$B$5:$B$304,A7))
I8: =IF(G8="","",G8-H8) | J8: =IF(OR(G8="",G8=0),"",I8/G8) | N8: =IF(A8="","",SUMIFS(Vendas!$E$5:$E$304,Vendas!$B$5:$B$304,A8)) | O8: =IF(A8="","",K8-N8) | P8: =IF(A8="","",SUMIFS(Vendas!$J$5:$J$304,Vendas!$B$5:$B$304,A8))
I9: =IF(G9="","",G9-H9) | J9: =IF(OR(G9="",G9=0),"",I9/G9) | N9: =IF(A9="","",SUMIFS(Vendas!$E$5:$E$304,Vendas!$B$5:$B$304,A9)) | O9: =IF(A9="","",K9-N9) | P9: =IF(A9="","",SUMIFS(Vendas!$J$5:$J$304,Vendas!$B$5:$B$304,A9))
I10: =IF(G10="","",G10-H10) | J10: =IF(OR(G10="",G10=0),"",I10/G10) | N10: =IF(A10="","",SUMIFS(Vendas!$E$5:$E$304,Vendas!$B$5:$B$304,A10)) | O10: =IF(A10="","",K10-N10) | P10: =IF(A10="","",SUMIFS(Vendas!$J$5:$J$304,Vendas!$B$5:$B$304,A10))
I11: =IF(G11="","",G11-H11) | J11: =IF(OR(G11="",G11=0),"",I11/G11) | N11: =IF(A11="","",SUMIFS(Vendas!$E$5:$E$304,Vendas!$B$5:$B$304,A11)) | O11: =IF(A11="","",K11-N11) | P11: =IF(A11="","",SUMIFS(Vendas!$J$5:$J$304,Vendas!$B$5:$B$304,A11))
I12: =IF(G12="","",G12-H12) | J12: =IF(OR(G12="",G12=0),"",I12/G12) | N12: =IF(A12="","",SUMIFS(Vendas!$E$5:$E$304,Vendas!$B$5:$B$304,A12)) | O12: =IF(A12="","",K12-N12) | P12: =IF(A12="","",SUMIFS(Vendas!$J$5:$J$304,Vendas!$B$5:$B$304,A12))
I13: =IF(G13="","",G13-H13) | J13: =IF(OR(G13="",G13=0),"",I13/G13) | N13: =IF(A13="","",SUMIFS(Vendas!$E$5:$E$304,Vendas!$B$5:$B$304,A13)) | O13: =IF(A13="","",K13-N13) | P13: =IF(A13="","",SUMIFS(Vendas!$J$5:$J$304,Vendas!$B$5:$B$304,A13))
I14: =IF(G14="","",G14-H14) | J14: =IF(OR(G14="",G14=0),"",I14/G14) | N14: =IF(A14="","",SUMIFS(Vendas!$E$5:$E$304,Vendas!$B$5:$B$304,A14)) | O14: =IF(A14="","",K14-N14) | P14: =IF(A14="","",SUMIFS(Vendas!$J$5:$J$304,Vendas!$B$5:$B$304,A14))
I15: =IF(G15="","",G15-H15) | J15: =IF(OR(G15="",G15=0),"",I15/G15) | N15: =IF(A15="","",SUMIFS(Vendas!$E$5:$E$304,Vendas!$B$5:$B$304,A15)) | O15: =IF(A15="","",K15-N15) | P15: =IF(A15="","",SUMIFS(Vendas!$J$5:$J$304,Vendas!$B$5:$B$304,A15))
I16: =IF(G16="","",G16-H16) | J16: =IF(OR(G16="",G16=0),"",I16/G16) | N16: =IF(A16="","",SUMIFS(Vendas!$E$5:$E$304,Vendas!$B$5:$B$304,A16)) | O16: =IF(A16="","",K16-N16) | P16: =IF(A16="","",SUMIFS(Vendas!$J$5:$J$304,Vendas!$B$5:$B$304,A16))
I17: =IF(G17="","",G17-H17) | J17: =IF(OR(G17="",G17=0),"",I17/G17) | N17: =IF(A17="","",SUMIFS(Vendas!$E$5:$E$304,Vendas!$B$5:$B$304,A17)) | O17: =IF(A17="","",K17-N17) | P17: =IF(A17="","",SUMIFS(Vendas!$J$5:$J$304,Vendas!$B$5:$B$304,A17))
I18: =IF(G18="","",G18-H18) | J18: =IF(OR(G18="",G18=0),"",I18/G18) | N18: =IF(A18="","",SUMIFS(Vendas!$E$5:$E$304,Vendas!$B$5:$B$304,A18)) | O18: =IF(A18="","",K18-N18) | P18: =IF(A18="","",SUMIFS(Vendas!$J$5:$J$304,Vendas!$B$5:$B$304,A18))
... I304: =IF(G304="","",G304-H304) | J304: =IF(OR(G304="",G304=0),"",I304/G304) | N304: =IF(A304="","",SUMIFS(Vendas!$E$5:$E$304,Vendas!$B$5:$B$304,A304)) | O304: =IF(A304="","",K304-N304) | P304: =IF(A304="","",SUMIFS(Vendas!$J$5:$J$304,Vendas!$B$5:$B$304,A304))

Sheet Autores
A1: Autores
A2: Autores e contratos. Royalties calculados sobre o preço de capa dos exemplares vendidos (padrão de mercado: 8–12%).
A4: Autor | B4: E-mail | C4: Telefone | D4: Cidade/UF | E4: Agente | F4: Nº contrato | G4: Início contrato | H4: Fim contrato | I4: % Royalties (s/ preço de capa) | J4: Adiantamento pago (R$) | K4: Royalties gerados (R$) | L4: Saldo a pagar (R$) | M4: Títulos no catálogo | N4: Redes sociais | O4: Observações
A5: Ana Exemplo | B5: ana@exemplo.com | C5: (11) 90000-0000 | D5: São Paulo/SP | E5: — | F5: C-2026-001 | G5: 46082 | H5: 47908 | I5: 0.1 | J5: 2000 | K5: =IF(A5="","",SUMIFS(Vendas!$I$5:$I$304,Vendas!$C$5:$C$304,A5)*I5) -> 419.4 | L5: =IF(A5="","",MAX(0,K5-J5)) -> 0 | M5: =IF(A5="","",COUNTIF(Catálogo!$C$5:$C$304,A5)) -> 1
A6: Bruno Exemplo | B6: bruno@exemplo.com | C6: (21) 90000-0000 | D6: Rio de Janeiro/RJ | E6: — | F6: C-2026-002 | G6: 46037 | H6: 47863 | I6: 0.1 | J6: 0 | K6: =IF(A6="","",SUMIFS(Vendas!$I$5:$I$304,Vendas!$C$5:$C$304,A6)*I6) -> 798.4 | L6: =IF(A6="","",MAX(0,K6-J6)) -> 798.4 | M6: =IF(A6="","",COUNTIF(Catálogo!$C$5:$C$304,A6)) -> 1
K7: =IF(A7="","",SUMIFS(Vendas!$I$5:$I$304,Vendas!$C$5:$C$304,A7)*I7) | L7: =IF(A7="","",MAX(0,K7-J7)) | M7: =IF(A7="","",COUNTIF(Catálogo!$C$5:$C$304,A7))
K8: =IF(A8="","",SUMIFS(Vendas!$I$5:$I$304,Vendas!$C$5:$C$304,A8)*I8) | L8: =IF(A8="","",MAX(0,K8-J8)) | M8: =IF(A8="","",COUNTIF(Catálogo!$C$5:$C$304,A8))
K9: =IF(A9="","",SUMIFS(Vendas!$I$5:$I$304,Vendas!$C$5:$C$304,A9)*I9) | L9: =IF(A9="","",MAX(0,K9-J9)) | M9: =IF(A9="","",COUNTIF(Catálogo!$C$5:$C$304,A9))
K10: =IF(A10="","",SUMIFS(Vendas!$I$5:$I$304,Vendas!$C$5:$C$304,A10)*I10) | L10: =IF(A10="","",MAX(0,K10-J10)) | M10: =IF(A10="","",COUNTIF(Catálogo!$C$5:$C$304,A10))
K11: =IF(A11="","",SUMIFS(Vendas!$I$5:$I$304,Vendas!$C$5:$C$304,A11)*I11) | L11: =IF(A11="","",MAX(0,K11-J11)) | M11: =IF(A11="","",COUNTIF(Catálogo!$C$5:$C$304,A11))
K12: =IF(A12="","",SUMIFS(Vendas!$I$5:$I$304,Vendas!$C$5:$C$304,A12)*I12) | L12: =IF(A12="","",MAX(0,K12-J12)) | M12: =IF(A12="","",COUNTIF(Catálogo!$C$5:$C$304,A12))
K13: =IF(A13="","",SUMIFS(Vendas!$I$5:$I$304,Vendas!$C$5:$C$304,A13)*I13) | L13: =IF(A13="","",MAX(0,K13-J13)) | M13: =IF(A13="","",COUNTIF(Catálogo!$C$5:$C$304,A13))
K14: =IF(A14="","",SUMIFS(Vendas!$I$5:$I$304,Vendas!$C$5:$C$304,A14)*I14) | L14: =IF(A14="","",MAX(0,K14-J14)) | M14: =IF(A14="","",COUNTIF(Catálogo!$C$5:$C$304,A14))
K15: =IF(A15="","",SUMIFS(Vendas!$I$5:$I$304,Vendas!$C$5:$C$304,A15)*I15) | L15: =IF(A15="","",MAX(0,K15-J15)) | M15: =IF(A15="","",COUNTIF(Catálogo!$C$5:$C$304,A15))
K16: =IF(A16="","",SUMIFS(Vendas!$I$5:$I$304,Vendas!$C$5:$C$304,A16)*I16) | L16: =IF(A16="","",MAX(0,K16-J16)) | M16: =IF(A16="","",COUNTIF(Catálogo!$C$5:$C$304,A16))
K17: =IF(A17="","",SUMIFS(Vendas!$I$5:$I$304,Vendas!$C$5:$C$304,A17)*I17) | L17: =IF(A17="","",MAX(0,K17-J17)) | M17: =IF(A17="","",COUNTIF(Catálogo!$C$5:$C$304,A17))
K18: =IF(A18="","",SUMIFS(Vendas!$I$5:$I$304,Vendas!$C$5:$C$304,A18)*I18) | L18: =IF(A18="","",MAX(0,K18-J18)) | M18: =IF(A18="","",COUNTIF(Catálogo!$C$5:$C$304,A18))
... K304: =IF(A304="","",SUMIFS(Vendas!$I$5:$I$304,Vendas!$C$5:$C$304,A304)*I304) | L304: =IF(A304="","",MAX(0,K304-J304)) | M304: =IF(A304="","",COUNTIF(Catálogo!$C$5:$C$304,A304))

Sheet Produção
A1: Produção
A2: Cronograma editorial: uma linha por etapa de cada título (original → gráfica → distribuição).
A4: Título | B4: Etapa | C4: Responsável | D4: Início | E4: Prazo | F4: Conclusão | G4: Status | H4: Dias de atraso | I4: Custo previsto (R$) | J4: Custo real (R$) | K4: Notas
A5: O Limiar | B5: Edição | C5: Editor(a) | D5: 46235 | E5: 46244 | F5: 46243 | G5: Concluído | H5: =IF(E5="","",IF(F5<>"",MAX(0,F5-E5),MAX(0,TODAY()-E5))) -> 0 | I5: 1500 | J5: 1500 | K5: Exemplo — substitua
A6: O Limiar | B6: Revisão | C6: Revisor(a) | D6: 46245 | E6: 46254 | F6: 46253 | G6: Concluído | H6: =IF(E6="","",IF(F6<>"",MAX(0,F6-E6),MAX(0,TODAY()-E6))) -> 0 | I6: 900 | J6: 950
A7: O Limiar | B7: Diagramação | C7: Designer | D7: 46255 | E7: 46264 | F7: 46263 | G7: Concluído | H7: =IF(E7="","",IF(F7<>"",MAX(0,F7-E7),MAX(0,TODAY()-E7))) -> 0 | I7: 800 | J7: 800
A8: O Limiar | B8: Capa | C8: Designer | D8: 46265 | E8: 46274 | G8: Em andamento | H8: =IF(E8="","",IF(F8<>"",MAX(0,F8-E8),MAX(0,TODAY()-E8))) -> 38 | I8: 1200
A9: O Limiar | B9: Gráfica | C9: Itar | D9: 46275 | E9: 46284 | G9: Não iniciado | H9: =IF(E9="","",IF(F9<>"",MAX(0,F9-E9),MAX(0,TODAY()-E9))) -> 28 | I9: 9800
H10: =IF(E10="","",IF(F10<>"",MAX(0,F10-E10),MAX(0,TODAY()-E10)))
H11: =IF(E11="","",IF(F11<>"",MAX(0,F11-E11),MAX(0,TODAY()-E11)))
H12: =IF(E12="","",IF(F12<>"",MAX(0,F12-E12),MAX(0,TODAY()-E12)))
H13: =IF(E13="","",IF(F13<>"",MAX(0,F13-E13),MAX(0,TODAY()-E13)))
H14: =IF(E14="","",IF(F14<>"",MAX(0,F14-E14),MAX(0,TODAY()-E14)))
H15: =IF(E15="","",IF(F15<>"",MAX(0,F15-E15),MAX(0,TODAY()-E15)))
H16: =IF(E16="","",IF(F16<>"",MAX(0,F16-E16),MAX(0,TODAY()-E16)))
H17: =IF(E17="","",IF(F17<>"",MAX(0,F17-E17),MAX(0,TODAY()-E17)))
H18: =IF(E18="","",IF(F18<>"",MAX(0,F18-E18),MAX(0,TODAY()-E18)))
H19: =IF(E19="","",IF(F19<>"",MAX(0,F19-E19),MAX(0,TODAY()-E19)))
H20: =IF(E20="","",IF(F20<>"",MAX(0,F20-E20),MAX(0,TODAY()-E20)))
H21: =IF(E21="","",IF(F21<>"",MAX(0,F21-E21),MAX(0,TODAY()-E21)))
... H304: =IF(E304="","",IF(F304<>"",MAX(0,F304-E304),MAX(0,TODAY()-E304)))

Sheet CRM_Contatos
A1: CRM Contatos
A2: Base de relacionamento: livrarias, distribuidores, imprensa, influenciadores, escolas, leitores.
A4: ID | B4: Nome / Empresa | C4: Tipo | D4: Pessoa de contato | E4: Cargo | F4: E-mail | G4: Telefone/WhatsApp | H4: Cidade/UF | I4: Origem | J4: Responsável | K4: Ativo? | L4: Última interação | M4: Nº interações | N4: Valor comprado (R$) | O4: Observações
A5: C001 | B5: Livraria Exemplo | C5: Livraria | D5: Carla | E5: Compradora | F5: compras@livrariaexemplo.com | G5: (11) 3000-0000 | H5: São Paulo/SP | I5: Feira | J5: Comercial | K5: Sim | L5: =IF(A5="","",IF(COUNTIF(CRM_Interações!$B$5:$B$304,A5)=0,"—",_xlfn.MAXIFS(CRM_Interações!$A$5:$A$304,CRM_Interações!$B$5:$B$304,A5))) -> 46305 | M5: =IF(A5="","",COUNTIF(CRM_Interações!$B$5:$B$304,A5)) -> 1 | N5: =IF(A5="","",SUMIFS(Vendas!$J$5:$J$304,Vendas!$G$5:$G$304,A5)) -> 0
A6: C002 | B6: Distribuidora Exemplo | C6: Distribuidora | D6: Diego | E6: Gerente | F6: diego@distexemplo.com | G6: (31) 3000-0000 | H6: Belo Horizonte/MG | I6: Prospecção ativa | J6: Itar | K6: Sim | L6: =IF(A6="","",IF(COUNTIF(CRM_Interações!$B$5:$B$304,A6)=0,"—",_xlfn.MAXIFS(CRM_Interações!$A$5:$A$304,CRM_Interações!$B$5:$B$304,A6))) -> — | M6: =IF(A6="","",COUNTIF(CRM_Interações!$B$5:$B$304,A6)) -> 0 | N6: =IF(A6="","",SUMIFS(Vendas!$J$5:$J$304,Vendas!$G$5:$G$304,A6)) -> 1098
A7: C003 | B7: @leiturasdaju | C7: Influenciador | D7: Juliana | E7: Criadora | F7: ju@exemplo.com | H7: Curitiba/PR | I7: Instagram | J7: Marketing | K7: Sim | L7: =IF(A7="","",IF(COUNTIF(CRM_Interações!$B$5:$B$304,A7)=0,"—",_xlfn.MAXIFS(CRM_Interações!$A$5:$A$304,CRM_Interações!$B$5:$B$304,A7))) -> 46309 | M7: =IF(A7="","",COUNTIF(CRM_Interações!$B$5:$B$304,A7)) -> 1 | N7: =IF(A7="","",SUMIFS(Vendas!$J$5:$J$304,Vendas!$G$5:$G$304,A7)) -> 0
L8: =IF(A8="","",IF(COUNTIF(CRM_Interações!$B$5:$B$304,A8)=0,"—",_xlfn.MAXIFS(CRM_Interações!$A$5:$A$304,CRM_Interações!$B$5:$B$304,A8))) | M8: =IF(A8="","",COUNTIF(CRM_Interações!$B$5:$B$304,A8)) | N8: =IF(A8="","",SUMIFS(Vendas!$J$5:$J$304,Vendas!$G$5:$G$304,A8))
L9: =IF(A9="","",IF(COUNTIF(CRM_Interações!$B$5:$B$304,A9)=0,"—",_xlfn.MAXIFS(CRM_Interações!$A$5:$A$304,CRM_Interações!$B$5:$B$304,A9))) | M9: =IF(A9="","",COUNTIF(CRM_Interações!$B$5:$B$304,A9)) | N9: =IF(A9="","",SUMIFS(Vendas!$J$5:$J$304,Vendas!$G$5:$G$304,A9))
L10: =IF(A10="","",IF(COUNTIF(CRM_Interações!$B$5:$B$304,A10)=0,"—",_xlfn.MAXIFS(CRM_Interações!$A$5:$A$304,CRM_Interações!$B$5:$B$304,A10))) | M10: =IF(A10="","",COUNTIF(CRM_Interações!$B$5:$B$304,A10)) | N10: =IF(A10="","",SUMIFS(Vendas!$J$5:$J$304,Vendas!$G$5:$G$304,A10))
L11: =IF(A11="","",IF(COUNTIF(CRM_Interações!$B$5:$B$304,A11)=0,"—",_xlfn.MAXIFS(CRM_Interações!$A$5:$A$304,CRM_Interações!$B$5:$B$304,A11))) | M11: =IF(A11="","",COUNTIF(CRM_Interações!$B$5:$B$304,A11)) | N11: =IF(A11="","",SUMIFS(Vendas!$J$5:$J$304,Vendas!$G$5:$G$304,A11))
L12: =IF(A12="","",IF(COUNTIF(CRM_Interações!$B$5:$B$304,A12)=0,"—",_xlfn.MAXIFS(CRM_Interações!$A$5:$A$304,CRM_Interações!$B$5:$B$304,A12))) | M12: =IF(A12="","",COUNTIF(CRM_Interações!$B$5:$B$304,A12)) | N12: =IF(A12="","",SUMIFS(Vendas!$J$5:$J$304,Vendas!$G$5:$G$304,A12))
L13: =IF(A13="","",IF(COUNTIF(CRM_Interações!$B$5:$B$304,A13)=0,"—",_xlfn.MAXIFS(CRM_Interações!$A$5:$A$304,CRM_Interações!$B$5:$B$304,A13))) | M13: =IF(A13="","",COUNTIF(CRM_Interações!$B$5:$B$304,A13)) | N13: =IF(A13="","",SUMIFS(Vendas!$J$5:$J$304,Vendas!$G$5:$G$304,A13))
L14: =IF(A14="","",IF(COUNTIF(CRM_Interações!$B$5:$B$304,A14)=0,"—",_xlfn.MAXIFS(CRM_Interações!$A$5:$A$304,CRM_Interações!$B$5:$B$304,A14))) | M14: =IF(A14="","",COUNTIF(CRM_Interações!$B$5:$B$304,A14)) | N14: =IF(A14="","",SUMIFS(Vendas!$J$5:$J$304,Vendas!$G$5:$G$304,A14))
L15: =IF(A15="","",IF(COUNTIF(CRM_Interações!$B$5:$B$304,A15)=0,"—",_xlfn.MAXIFS(CRM_Interações!$A$5:$A$304,CRM_Interações!$B$5:$B$304,A15))) | M15: =IF(A15="","",COUNTIF(CRM_Interações!$B$5:$B$304,A15)) | N15: =IF(A15="","",SUMIFS(Vendas!$J$5:$J$304,Vendas!$G$5:$G$304,A15))
L16: =IF(A16="","",IF(COUNTIF(CRM_Interações!$B$5:$B$304,A16)=0,"—",_xlfn.MAXIFS(CRM_Interações!$A$5:$A$304,CRM_Interações!$B$5:$B$304,A16))) | M16: =IF(A16="","",COUNTIF(CRM_Interações!$B$5:$B$304,A16)) | N16: =IF(A16="","",SUMIFS(Vendas!$J$5:$J$304,Vendas!$G$5:$G$304,A16))
L17: =IF(A17="","",IF(COUNTIF(CRM_Interações!$B$5:$B$304,A17)=0,"—",_xlfn.MAXIFS(CRM_Interações!$A$5:$A$304,CRM_Interações!$B$5:$B$304,A17))) | M17: =IF(A17="","",COUNTIF(CRM_Interações!$B$5:$B$304,A17)) | N17: =IF(A17="","",SUMIFS(Vendas!$J$5:$J$304,Vendas!$G$5:$G$304,A17))
L18: =IF(A18="","",IF(COUNTIF(CRM_Interações!$B$5:$B$304,A18)=0,"—",_xlfn.MAXIFS(CRM_Interações!$A$5:$A$304,CRM_Interações!$B$5:$B$304,A18))) | M18: =IF(A18="","",COUNTIF(CRM_Interações!$B$5:$B$304,A18)) | N18: =IF(A18="","",SUMIFS(Vendas!$J$5:$J$304,Vendas!$G$5:$G$304,A18))
L19: =IF(A19="","",IF(COUNTIF(CRM_Interações!$B$5:$B$304,A19)=0,"—",_xlfn.MAXIFS(CRM_Interações!$A$5:$A$304,CRM_Interações!$B$5:$B$304,A19))) | M19: =IF(A19="","",COUNTIF(CRM_Interações!$B$5:$B$304,A19)) | N19: =IF(A19="","",SUMIFS(Vendas!$J$5:$J$304,Vendas!$G$5:$G$304,A19))
... L304: =IF(A304="","",IF(COUNTIF(CRM_Interações!$B$5:$B$304,A304)=0,"—",_xlfn.MAXIFS(CRM_Interações!$A$5:$A$304,CRM_Interações!$B$5:$B$304,A304))) | M304: =IF(A304="","",COUNTIF(CRM_Interações!$B$5:$B$304,A304)) | N304: =IF(A304="","",SUMIFS(Vendas!$J$5:$J$304,Vendas!$G$5:$G$304,A304))

Sheet CRM_Pipeline
A1: CRM Pipeline
A2: Funil de vendas B2B: consignação em livrarias, pedidos de distribuidoras, compras de escolas/governo, parcerias.
A4: ID contato | B4: Contato | C4: Oportunidade | D4: Título(s) | E4: Etapa do funil | F4: Valor estimado (R$) | G4: Probabilidade | H4: Valor ponderado (R$) | I4: Responsável | J4: Próxima ação | K4: Data próxima ação | L4: Situação | M4: Data fechamento prevista
A5: C001 | B5: =IF(A5="","",IFERROR(INDEX(CRM_Contatos!$B$5:$B$304,MATCH(A5,CRM_Contatos!$A$5:$A$304,0)),"ID não encontrado")) -> Livraria Exemplo | C5: Pedido de lançamento — 30 exemplares | D5: O Limiar | E5: Proposta | F5: 1258.2 | G5: =IF(E5="","",IFERROR(INDEX(Listas!$O$4:$O$10,MATCH(E5,Listas!$N$4:$N$10,0)),0)) -> 0.5 | H5: =IF(OR(F5="",G5=""),"",F5*G5) -> 629.1 | I5: Comercial | J5: Enviar condições de consignação | K5: 46317 | L5: =IF(K5="","",IF(LEFT(E5,7)="Fechado","Encerrada",IF(K5<TODAY(),"Atrasada",IF(K5-TODAY()<=3,"Esta semana","No prazo")))) -> No prazo | M5: 46331
A6: C002 | B6: =IF(A6="","",IFERROR(INDEX(CRM_Contatos!$B$5:$B$304,MATCH(A6,CRM_Contatos!$A$5:$A$304,0)),"ID não encontrado")) -> Distribuidora Exemplo | C6: Entrada no catálogo da distribuidora | D6: Todos | E6: Negociação | F6: 8000 | G6: =IF(E6="","",IFERROR(INDEX(Listas!$O$4:$O$10,MATCH(E6,Listas!$N$4:$N$10,0)),0)) -> 0.75 | H6: =IF(OR(F6="",G6=""),"",F6*G6) -> 6000 | I6: Itar | J6: Reunião de fechamento | K6: 46320 | L6: =IF(K6="","",IF(LEFT(E6,7)="Fechado","Encerrada",IF(K6<TODAY(),"Atrasada",IF(K6-TODAY()<=3,"Esta semana","No prazo")))) -> No prazo | M6: 46341
B7: =IF(A7="","",IFERROR(INDEX(CRM_Contatos!$B$5:$B$304,MATCH(A7,CRM_Contatos!$A$5:$A$304,0)),"ID não encontrado")) | G7: =IF(E7="","",IFERROR(INDEX(Listas!$O$4:$O$10,MATCH(E7,Listas!$N$4:$N$10,0)),0)) | H7: =IF(OR(F7="",G7=""),"",F7*G7) | L7: =IF(K7="","",IF(LEFT(E7,7)="Fechado","Encerrada",IF(K7<TODAY(),"Atrasada",IF(K7-TODAY()<=3,"Esta semana","No prazo"))))
B8: =IF(A8="","",IFERROR(INDEX(CRM_Contatos!$B$5:$B$304,MATCH(A8,CRM_Contatos!$A$5:$A$304,0)),"ID não encontrado")) | G8: =IF(E8="","",IFERROR(INDEX(Listas!$O$4:$O$10,MATCH(E8,Listas!$N$4:$N$10,0)),0)) | H8: =IF(OR(F8="",G8=""),"",F8*G8) | L8: =IF(K8="","",IF(LEFT(E8,7)="Fechado","Encerrada",IF(K8<TODAY(),"Atrasada",IF(K8-TODAY()<=3,"Esta semana","No prazo"))))
B9: =IF(A9="","",IFERROR(INDEX(CRM_Contatos!$B$5:$B$304,MATCH(A9,CRM_Contatos!$A$5:$A$304,0)),"ID não encontrado")) | G9: =IF(E9="","",IFERROR(INDEX(Listas!$O$4:$O$10,MATCH(E9,Listas!$N$4:$N$10,0)),0)) | H9: =IF(OR(F9="",G9=""),"",F9*G9) | L9: =IF(K9="","",IF(LEFT(E9,7)="Fechado","Encerrada",IF(K9<TODAY(),"Atrasada",IF(K9-TODAY()<=3,"Esta semana","No prazo"))))
B10: =IF(A10="","",IFERROR(INDEX(CRM_Contatos!$B$5:$B$304,MATCH(A10,CRM_Contatos!$A$5:$A$304,0)),"ID não encontrado")) | G10: =IF(E10="","",IFERROR(INDEX(Listas!$O$4:$O$10,MATCH(E10,Listas!$N$4:$N$10,0)),0)) | H10: =IF(OR(F10="",G10=""),"",F10*G10) | L10: =IF(K10="","",IF(LEFT(E10,7)="Fechado","Encerrada",IF(K10<TODAY(),"Atrasada",IF(K10-TODAY()<=3,"Esta semana","No prazo"))))
B11: =IF(A11="","",IFERROR(INDEX(CRM_Contatos!$B$5:$B$304,MATCH(A11,CRM_Contatos!$A$5:$A$304,0)),"ID não encontrado")) | G11: =IF(E11="","",IFERROR(INDEX(Listas!$O$4:$O$10,MATCH(E11,Listas!$N$4:$N$10,0)),0)) | H11: =IF(OR(F11="",G11=""),"",F11*G11) | L11: =IF(K11="","",IF(LEFT(E11,7)="Fechado","Encerrada",IF(K11<TODAY(),"Atrasada",IF(K11-TODAY()<=3,"Esta semana","No prazo"))))
B12: =IF(A12="","",IFERROR(INDEX(CRM_Contatos!$B$5:$B$304,MATCH(A12,CRM_Contatos!$A$5:$A$304,0)),"ID não encontrado")) | G12: =IF(E12="","",IFERROR(INDEX(Listas!$O$4:$O$10,MATCH(E12,Listas!$N$4:$N$10,0)),0)) | H12: =IF(OR(F12="",G12=""),"",F12*G12) | L12: =IF(K12="","",IF(LEFT(E12,7)="Fechado","Encerrada",IF(K12<TODAY(),"Atrasada",IF(K12-TODAY()<=3,"Esta semana","No prazo"))))
B13: =IF(A13="","",IFERROR(INDEX(CRM_Contatos!$B$5:$B$304,MATCH(A13,CRM_Contatos!$A$5:$A$304,0)),"ID não encontrado")) | G13: =IF(E13="","",IFERROR(INDEX(Listas!$O$4:$O$10,MATCH(E13,Listas!$N$4:$N$10,0)),0)) | H13: =IF(OR(F13="",G13=""),"",F13*G13) | L13: =IF(K13="","",IF(LEFT(E13,7)="Fechado","Encerrada",IF(K13<TODAY(),"Atrasada",IF(K13-TODAY()<=3,"Esta semana","No prazo"))))
B14: =IF(A14="","",IFERROR(INDEX(CRM_Contatos!$B$5:$B$304,MATCH(A14,CRM_Contatos!$A$5:$A$304,0)),"ID não encontrado")) | G14: =IF(E14="","",IFERROR(INDEX(Listas!$O$4:$O$10,MATCH(E14,Listas!$N$4:$N$10,0)),0)) | H14: =IF(OR(F14="",G14=""),"",F14*G14) | L14: =IF(K14="","",IF(LEFT(E14,7)="Fechado","Encerrada",IF(K14<TODAY(),"Atrasada",IF(K14-TODAY()<=3,"Esta semana","No prazo"))))
B15: =IF(A15="","",IFERROR(INDEX(CRM_Contatos!$B$5:$B$304,MATCH(A15,CRM_Contatos!$A$5:$A$304,0)),"ID não encontrado")) | G15: =IF(E15="","",IFERROR(INDEX(Listas!$O$4:$O$10,MATCH(E15,Listas!$N$4:$N$10,0)),0)) | H15: =IF(OR(F15="",G15=""),"",F15*G15) | L15: =IF(K15="","",IF(LEFT(E15,7)="Fechado","Encerrada",IF(K15<TODAY(),"Atrasada",IF(K15-TODAY()<=3,"Esta semana","No prazo"))))
B16: =IF(A16="","",IFERROR(INDEX(CRM_Contatos!$B$5:$B$304,MATCH(A16,CRM_Contatos!$A$5:$A$304,0)),"ID não encontrado")) | G16: =IF(E16="","",IFERROR(INDEX(Listas!$O$4:$O$10,MATCH(E16,Listas!$N$4:$N$10,0)),0)) | H16: =IF(OR(F16="",G16=""),"",F16*G16) | L16: =IF(K16="","",IF(LEFT(E16,7)="Fechado","Encerrada",IF(K16<TODAY(),"Atrasada",IF(K16-TODAY()<=3,"Esta semana","No prazo"))))
B17: =IF(A17="","",IFERROR(INDEX(CRM_Contatos!$B$5:$B$304,MATCH(A17,CRM_Contatos!$A$5:$A$304,0)),"ID não encontrado")) | G17: =IF(E17="","",IFERROR(INDEX(Listas!$O$4:$O$10,MATCH(E17,Listas!$N$4:$N$10,0)),0)) | H17: =IF(OR(F17="",G17=""),"",F17*G17) | L17: =IF(K17="","",IF(LEFT(E17,7)="Fechado","Encerrada",IF(K17<TODAY(),"Atrasada",IF(K17-TODAY()<=3,"Esta semana","No prazo"))))
B18: =IF(A18="","",IFERROR(INDEX(CRM_Contatos!$B$5:$B$304,MATCH(A18,CRM_Contatos!$A$5:$A$304,0)),"ID não encontrado")) | G18: =IF(E18="","",IFERROR(INDEX(Listas!$O$4:$O$10,MATCH(E18,Listas!$N$4:$N$10,0)),0)) | H18: =IF(OR(F18="",G18=""),"",F18*G18) | L18: =IF(K18="","",IF(LEFT(E18,7)="Fechado","Encerrada",IF(K18<TODAY(),"Atrasada",IF(K18-TODAY()<=3,"Esta semana","No prazo"))))
... B304: =IF(A304="","",IFERROR(INDEX(CRM_Contatos!$B$5:$B$304,MATCH(A304,CRM_Contatos!$A$5:$A$304,0)),"ID não encontrado")) | G304: =IF(E304="","",IFERROR(INDEX(Listas!$O$4:$O$10,MATCH(E304,Listas!$N$4:$N$10,0)),0)) | H304: =IF(OR(F304="",G304=""),"",F304*G304) | L304: =IF(K304="","",IF(LEFT(E304,7)="Fechado","Encerrada",IF(K304<TODAY(),"Atrasada",IF(K304-TODAY()<=3,"Esta semana","No prazo"))))

Sheet CRM_Interações
A1: CRM Interações
A2: Histórico de cada contato (ligações, e-mails, reuniões, amostras enviadas). Alimenta 'Última interação' no CRM.
A4: Data | B4: ID contato | C4: Contato | D4: Tipo | E4: Resumo | F4: Resultado / Próximo passo | G4: Responsável
A5: 46305 | B5: C001 | C5: =IF(B5="","",IFERROR(INDEX(CRM_Contatos!$B$5:$B$304,MATCH(B5,CRM_Contatos!$A$5:$A$304,0)),"ID não encontrado")) -> Livraria Exemplo | D5: E-mail | E5: Apresentação do lançamento O Limiar | F5: Pediu condições de consignação | G5: Comercial
A6: 46309 | B6: C003 | C6: =IF(B6="","",IFERROR(INDEX(CRM_Contatos!$B$5:$B$304,MATCH(B6,CRM_Contatos!$A$5:$A$304,0)),"ID não encontrado")) -> @leiturasdaju | D6: Envio de amostra | E6: Envio de exemplar de cortesia | F6: Resenha prevista para novembro | G6: Marketing
C7: =IF(B7="","",IFERROR(INDEX(CRM_Contatos!$B$5:$B$304,MATCH(B7,CRM_Contatos!$A$5:$A$304,0)),"ID não encontrado"))
C8: =IF(B8="","",IFERROR(INDEX(CRM_Contatos!$B$5:$B$304,MATCH(B8,CRM_Contatos!$A$5:$A$304,0)),"ID não encontrado"))
C9: =IF(B9="","",IFERROR(INDEX(CRM_Contatos!$B$5:$B$304,MATCH(B9,CRM_Contatos!$A$5:$A$304,0)),"ID não encontrado"))
C10: =IF(B10="","",IFERROR(INDEX(CRM_Contatos!$B$5:$B$304,MATCH(B10,CRM_Contatos!$A$5:$A$304,0)),"ID não encontrado"))
C11: =IF(B11="","",IFERROR(INDEX(CRM_Contatos!$B$5:$B$304,MATCH(B11,CRM_Contatos!$A$5:$A$304,0)),"ID não encontrado"))
C12: =IF(B12="","",IFERROR(INDEX(CRM_Contatos!$B$5:$B$304,MATCH(B12,CRM_Contatos!$A$5:$A$304,0)),"ID não encontrado"))
C13: =IF(B13="","",IFERROR(INDEX(CRM_Contatos!$B$5:$B$304,MATCH(B13,CRM_Contatos!$A$5:$A$304,0)),"ID não encontrado"))
C14: =IF(B14="","",IFERROR(INDEX(CRM_Contatos!$B$5:$B$304,MATCH(B14,CRM_Contatos!$A$5:$A$304,0)),"ID não encontrado"))
C15: =IF(B15="","",IFERROR(INDEX(CRM_Contatos!$B$5:$B$304,MATCH(B15,CRM_Contatos!$A$5:$A$304,0)),"ID não encontrado"))
C16: =IF(B16="","",IFERROR(INDEX(CRM_Contatos!$B$5:$B$304,MATCH(B16,CRM_Contatos!$A$5:$A$304,0)),"ID não encontrado"))
C17: =IF(B17="","",IFERROR(INDEX(CRM_Contatos!$B$5:$B$304,MATCH(B17,CRM_Contatos!$A$5:$A$304,0)),"ID não encontrado"))
C18: =IF(B18="","",IFERROR(INDEX(CRM_Contatos!$B$5:$B$304,MATCH(B18,CRM_Contatos!$A$5:$A$304,0)),"ID não encontrado"))
... C304: =IF(B304="","",IFERROR(INDEX(CRM_Contatos!$B$5:$B$304,MATCH(B304,CRM_Contatos!$A$5:$A$304,0)),"ID não encontrado"))

Sheet Vendas
A1: Vendas
A2: Uma linha por venda/pedido. Informe o preço efetivamente cobrado; o desconto sobre o preço de capa é calculado.
A4: Data | B4: ISBN | C4: Autor | D4: Título | E4: Quantidade | F4: Preço unitário (R$) | G4: ID cliente | H4: Canal | I4: Valor de capa (R$) | J4: Receita líquida (R$) | K4: Desconto concedido % | L4: Nº pedido / NF
A5: 46244 | B5: 978-65-00000-02-8 | C5: =IF(B5="","",IFERROR(INDEX(Catálogo!$C$5:$C$304,MATCH(B5,Catálogo!$A$5:$A$304,0)),"ISBN não cadastrado")) -> Bruno Exemplo | D5: =IF(B5="","",IFERROR(INDEX(Catálogo!$B$5:$B$304,MATCH(B5,Catálogo!$A$5:$A$304,0)),"ISBN não cadastrado")) -> Cartas ao Mar | E5: 120 | F5: 49.9 | H5: Site próprio | I5: =IF(B5="","",E5*IFERROR(INDEX(Catálogo!$G$5:$G$304,MATCH(B5,Catálogo!$A$5:$A$304,0)),0)) -> 5988 | J5: =IF(B5="","",E5*F5) -> 5988 | K5: =IF(OR(B5="",I5=0),"",1-J5/I5) -> 0 | L5: PED-0001
A6: 46267 | B6: 978-65-00000-02-8 | C6: =IF(B6="","",IFERROR(INDEX(Catálogo!$C$5:$C$304,MATCH(B6,Catálogo!$A$5:$A$304,0)),"ISBN não cadastrado")) -> Bruno Exemplo | D6: =IF(B6="","",IFERROR(INDEX(Catálogo!$B$5:$B$304,MATCH(B6,Catálogo!$A$5:$A$304,0)),"ISBN não cadastrado")) -> Cartas ao Mar | E6: 40 | F6: 27.45 | G6: C002 | H6: Distribuidora | I6: =IF(B6="","",E6*IFERROR(INDEX(Catálogo!$G$5:$G$304,MATCH(B6,Catálogo!$A$5:$A$304,0)),0)) -> 1996 | J6: =IF(B6="","",E6*F6) -> 1098 | K6: =IF(OR(B6="",I6=0),"",1-J6/I6) -> 0.4498998 | L6: NF-0001
A7: 46296 | B7: 978-65-00000-01-1 | C7: =IF(B7="","",IFERROR(INDEX(Catálogo!$C$5:$C$304,MATCH(B7,Catálogo!$A$5:$A$304,0)),"ISBN não cadastrado")) -> Ana Exemplo | D7: =IF(B7="","",IFERROR(INDEX(Catálogo!$B$5:$B$304,MATCH(B7,Catálogo!$A$5:$A$304,0)),"ISBN não cadastrado")) -> O Limiar | E7: 60 | F7: 59.9 | H7: Site próprio | I7: =IF(B7="","",E7*IFERROR(INDEX(Catálogo!$G$5:$G$304,MATCH(B7,Catálogo!$A$5:$A$304,0)),0)) -> 4194 | J7: =IF(B7="","",E7*F7) -> 3594 | K7: =IF(OR(B7="",I7=0),"",1-J7/I7) -> 0.14306152 | L7: PED-0002
C8: =IF(B8="","",IFERROR(INDEX(Catálogo!$C$5:$C$304,MATCH(B8,Catálogo!$A$5:$A$304,0)),"ISBN não cadastrado")) | D8: =IF(B8="","",IFERROR(INDEX(Catálogo!$B$5:$B$304,MATCH(B8,Catálogo!$A$5:$A$304,0)),"ISBN não cadastrado")) | I8: =IF(B8="","",E8*IFERROR(INDEX(Catálogo!$G$5:$G$304,MATCH(B8,Catálogo!$A$5:$A$304,0)),0)) | J8: =IF(B8="","",E8*F8) | K8: =IF(OR(B8="",I8=0),"",1-J8/I8)
C9: =IF(B9="","",IFERROR(INDEX(Catálogo!$C$5:$C$304,MATCH(B9,Catálogo!$A$5:$A$304,0)),"ISBN não cadastrado")) | D9: =IF(B9="","",IFERROR(INDEX(Catálogo!$B$5:$B$304,MATCH(B9,Catálogo!$A$5:$A$304,0)),"ISBN não cadastrado")) | I9: =IF(B9="","",E9*IFERROR(INDEX(Catálogo!$G$5:$G$304,MATCH(B9,Catálogo!$A$5:$A$304,0)),0)) | J9: =IF(B9="","",E9*F9) | K9: =IF(OR(B9="",I9=0),"",1-J9/I9)
C10: =IF(B10="","",IFERROR(INDEX(Catálogo!$C$5:$C$304,MATCH(B10,Catálogo!$A$5:$A$304,0)),"ISBN não cadastrado")) | D10: =IF(B10="","",IFERROR(INDEX(Catálogo!$B$5:$B$304,MATCH(B10,Catálogo!$A$5:$A$304,0)),"ISBN não cadastrado")) | I10: =IF(B10="","",E10*IFERROR(INDEX(Catálogo!$G$5:$G$304,MATCH(B10,Catálogo!$A$5:$A$304,0)),0)) | J10: =IF(B10="","",E10*F10) | K10: =IF(OR(B10="",I10=0),"",1-J10/I10)
C11: =IF(B11="","",IFERROR(INDEX(Catálogo!$C$5:$C$304,MATCH(B11,Catálogo!$A$5:$A$304,0)),"ISBN não cadastrado")) | D11: =IF(B11="","",IFERROR(INDEX(Catálogo!$B$5:$B$304,MATCH(B11,Catálogo!$A$5:$A$304,0)),"ISBN não cadastrado")) | I11: =IF(B11="","",E11*IFERROR(INDEX(Catálogo!$G$5:$G$304,MATCH(B11,Catálogo!$A$5:$A$304,0)),0)) | J11: =IF(B11="","",E11*F11) | K11: =IF(OR(B11="",I11=0),"",1-J11/I11)
C12: =IF(B12="","",IFERROR(INDEX(Catálogo!$C$5:$C$304,MATCH(B12,Catálogo!$A$5:$A$304,0)),"ISBN não cadastrado")) | D12: =IF(B12="","",IFERROR(INDEX(Catálogo!$B$5:$B$304,MATCH(B12,Catálogo!$A$5:$A$304,0)),"ISBN não cadastrado")) | I12: =IF(B12="","",E12*IFERROR(INDEX(Catálogo!$G$5:$G$304,MATCH(B12,Catálogo!$A$5:$A$304,0)),0)) | J12: =IF(B12="","",E12*F12) | K12: =IF(OR(B12="",I12=0),"",1-J12/I12)
C13: =IF(B13="","",IFERROR(INDEX(Catálogo!$C$5:$C$304,MATCH(B13,Catálogo!$A$5:$A$304,0)),"ISBN não cadastrado")) | D13: =IF(B13="","",IFERROR(INDEX(Catálogo!$B$5:$B$304,MATCH(B13,Catálogo!$A$5:$A$304,0)),"ISBN não cadastrado")) | I13: =IF(B13="","",E13*IFERROR(INDEX(Catálogo!$G$5:$G$304,MATCH(B13,Catálogo!$A$5:$A$304,0)),0)) | J13: =IF(B13="","",E13*F13) | K13: =IF(OR(B13="",I13=0),"",1-J13/I13)
C14: =IF(B14="","",IFERROR(INDEX(Catálogo!$C$5:$C$304,MATCH(B14,Catálogo!$A$5:$A$304,0)),"ISBN não cadastrado")) | D14: =IF(B14="","",IFERROR(INDEX(Catálogo!$B$5:$B$304,MATCH(B14,Catálogo!$A$5:$A$304,0)),"ISBN não cadastrado")) | I14: =IF(B14="","",E14*IFERROR(INDEX(Catálogo!$G$5:$G$304,MATCH(B14,Catálogo!$A$5:$A$304,0)),0)) | J14: =IF(B14="","",E14*F14) | K14: =IF(OR(B14="",I14=0),"",1-J14/I14)
C15: =IF(B15="","",IFERROR(INDEX(Catálogo!$C$5:$C$304,MATCH(B15,Catálogo!$A$5:$A$304,0)),"ISBN não cadastrado")) | D15: =IF(B15="","",IFERROR(INDEX(Catálogo!$B$5:$B$304,MATCH(B15,Catálogo!$A$5:$A$304,0)),"ISBN não cadastrado")) | I15: =IF(B15="","",E15*IFERROR(INDEX(Catálogo!$G$5:$G$304,MATCH(B15,Catálogo!$A$5:$A$304,0)),0)) | J15: =IF(B15="","",E15*F15) | K15: =IF(OR(B15="",I15=0),"",1-J15/I15)
C16: =IF(B16="","",IFERROR(INDEX(Catálogo!$C$5:$C$304,MATCH(B16,Catálogo!$A$5:$A$304,0)),"ISBN não cadastrado")) | D16: =IF(B16="","",IFERROR(INDEX(Catálogo!$B$5:$B$304,MATCH(B16,Catálogo!$A$5:$A$304,0)),"ISBN não cadastrado")) | I16: =IF(B16="","",E16*IFERROR(INDEX(Catálogo!$G$5:$G$304,MATCH(B16,Catálogo!$A$5:$A$304,0)),0)) | J16: =IF(B16="","",E16*F16) | K16: =IF(OR(B16="",I16=0),"",1-J16/I16)
C17: =IF(B17="","",IFERROR(INDEX(Catálogo!$C$5:$C$304,MATCH(B17,Catálogo!$A$5:$A$304,0)),"ISBN não cadastrado")) | D17: =IF(B17="","",IFERROR(INDEX(Catálogo!$B$5:$B$304,MATCH(B17,Catálogo!$A$5:$A$304,0)),"ISBN não cadastrado")) | I17: =IF(B17="","",E17*IFERROR(INDEX(Catálogo!$G$5:$G$304,MATCH(B17,Catálogo!$A$5:$A$304,0)),0)) | J17: =IF(B17="","",E17*F17) | K17: =IF(OR(B17="",I17=0),"",1-J17/I17)
C18: =IF(B18="","",IFERROR(INDEX(Catálogo!$C$5:$C$304,MATCH(B18,Catálogo!$A$5:$A$304,0)),"ISBN não cadastrado")) | D18: =IF(B18="","",IFERROR(INDEX(Catálogo!$B$5:$B$304,MATCH(B18,Catálogo!$A$5:$A$304,0)),"ISBN não cadastrado")) | I18: =IF(B18="","",E18*IFERROR(INDEX(Catálogo!$G$5:$G$304,MATCH(B18,Catálogo!$A$5:$A$304,0)),0)) | J18: =IF(B18="","",E18*F18) | K18: =IF(OR(B18="",I18=0),"",1-J18/I18)
C19: =IF(B19="","",IFERROR(INDEX(Catálogo!$C$5:$C$304,MATCH(B19,Catálogo!$A$5:$A$304,0)),"ISBN não cadastrado")) | D19: =IF(B19="","",IFERROR(INDEX(Catálogo!$B$5:$B$304,MATCH(B19,Catálogo!$A$5:$A$304,0)),"ISBN não cadastrado")) | I19: =IF(B19="","",E19*IFERROR(INDEX(Catálogo!$G$5:$G$304,MATCH(B19,Catálogo!$A$5:$A$304,0)),0)) | J19: =IF(B19="","",E19*F19) | K19: =IF(OR(B19="",I19=0),"",1-J19/I19)
... C304: =IF(B304="","",IFERROR(INDEX(Catálogo!$C$5:$C$304,MATCH(B304,Catálogo!$A$5:$A$304,0)),"ISBN não cadastrado")) | D304: =IF(B304="","",IFERROR(INDEX(Catálogo!$B$5:$B$304,MATCH(B304,Catálogo!$A$5:$A$304,0)),"ISBN não cadastrado")) | I304: =IF(B304="","",E304*IFERROR(INDEX(Catálogo!$G$5:$G$304,MATCH(B304,Catálogo!$A$5:$A$304,0)),0)) | J304: =IF(B304="","",E304*F304) | K304: =IF(OR(B304="",I304=0),"",1-J304/I304)

Sheet Financeiro
A1: Financeiro
A2: Fluxo de caixa: todas as receitas e despesas. Despesas entram como valor positivo; o sinal é aplicado automaticamente.
A4: Data | B4: Tipo | C4: Categoria | D4: Descrição | E4: Título relacionado | F4: Valor (R$) | G4: Valor com sinal (R$) | H4: Pago/Recebido? | I4: Mês
A5: 46239 | B5: Despesa | C5: Revisão/Edição | D5: Revisão — Cartas ao Mar | E5: Cartas ao Mar | F5: 900 | G5: =IF(F5="","",IF(B5="Despesa",-F5,F5)) -> -900 | H5: Sim | I5: =IF(A5="","",TEXT(A5,"yyyy-mm")) -> 2026-08
A6: 46254 | B6: Despesa | C6: Gráfica | D6: Impressão 500 ex. — Cartas ao Mar | E6: Cartas ao Mar | F6: 4900 | G6: =IF(F6="","",IF(B6="Despesa",-F6,F6)) -> -4900 | H6: Sim | I6: =IF(A6="","",TEXT(A6,"yyyy-mm")) -> 2026-08
A7: 46265 | B7: Receita | C7: Venda de livros | D7: Vendas site — agosto | E7: Cartas ao Mar | F7: 5988 | G7: =IF(F7="","",IF(B7="Despesa",-F7,F7)) -> 5988 | H7: Sim | I7: =IF(A7="","",TEXT(A7,"yyyy-mm")) -> 2026-08
A8: 46275 | B8: Despesa | C8: Marketing | D8: Impulsionamento Instagram | F8: 400 | G8: =IF(F8="","",IF(B8="Despesa",-F8,F8)) -> -400 | H8: Sim | I8: =IF(A8="","",TEXT(A8,"yyyy-mm")) -> 2026-09
G9: =IF(F9="","",IF(B9="Despesa",-F9,F9)) | I9: =IF(A9="","",TEXT(A9,"yyyy-mm"))
G10: =IF(F10="","",IF(B10="Despesa",-F10,F10)) | I10: =IF(A10="","",TEXT(A10,"yyyy-mm"))
G11: =IF(F11="","",IF(B11="Despesa",-F11,F11)) | I11: =IF(A11="","",TEXT(A11,"yyyy-mm"))
G12: =IF(F12="","",IF(B12="Despesa",-F12,F12)) | I12: =IF(A12="","",TEXT(A12,"yyyy-mm"))
G13: =IF(F13="","",IF(B13="Despesa",-F13,F13)) | I13: =IF(A13="","",TEXT(A13,"yyyy-mm"))
G14: =IF(F14="","",IF(B14="Despesa",-F14,F14)) | I14: =IF(A14="","",TEXT(A14,"yyyy-mm"))
G15: =IF(F15="","",IF(B15="Despesa",-F15,F15)) | I15: =IF(A15="","",TEXT(A15,"yyyy-mm"))
G16: =IF(F16="","",IF(B16="Despesa",-F16,F16)) | I16: =IF(A16="","",TEXT(A16,"yyyy-mm"))
G17: =IF(F17="","",IF(B17="Despesa",-F17,F17)) | I17: =IF(A17="","",TEXT(A17,"yyyy-mm"))
G18: =IF(F18="","",IF(B18="Despesa",-F18,F18)) | I18: =IF(A18="","",TEXT(A18,"yyyy-mm"))
G19: =IF(F19="","",IF(B19="Despesa",-F19,F19)) | I19: =IF(A19="","",TEXT(A19,"yyyy-mm"))
G20: =IF(F20="","",IF(B20="Despesa",-F20,F20)) | I20: =IF(A20="","",TEXT(A20,"yyyy-mm"))
... G304: =IF(F304="","",IF(B304="Despesa",-F304,F304)) | I304: =IF(A304="","",TEXT(A304,"yyyy-mm"))

Sheet Listas
A1: Listas (edite aqui as opções dos menus suspensos)
A3: Gênero | B3: Formato | C3: Status título | D3: Etapa produção | E3: Status tarefa | F3: Tipo contato | G3: Canal venda | H3: Origem lead | I3: Tipo interação | J3: Tipo lançamento | K3: Categoria fin. | L3: Responsável | N3: Etapa funil | O3: Probabilidade
A4: Romance | B4: Brochura | C4: Em avaliação | D4: Recebimento de original | E4: Não iniciado | F4: Livraria | G4: Site próprio | H4: Indicação | I4: Ligação | J4: Receita | K4: Venda de livros | L4: Itar | N4: Lead | O4: 0.1
A5: Contos | B5: Capa dura | C5: Contratado | D5: Leitura crítica | E5: Em andamento | F5: Distribuidora | G5: Amazon | H5: Instagram | I5: E-mail | J5: Despesa | K5: Direitos/Licenciamento | L5: Editor(a) | N5: Contato feito | O5: 0.2
A6: Poesia | B6: E-book | C6: Em produção | D6: Edição | E6: Aguardando | F6: Marketplace | G6: Livrarias | H6: Site | I6: WhatsApp | K6: Edital/Incentivo | L6: Revisor(a) | N6: Amostra enviada | O6: 0.35
A7: Não-ficção | B7: Audiolivro | C7: Pré-venda | D7: Preparação de texto | E7: Concluído | F7: Escola/Governo | G7: Distribuidora | H7: Feira | I7: Reunião | K7: Gráfica | L7: Designer | N7: Proposta | O7: 0.5
A8: Biografia | B8: Box | C8: Publicado | D8: Revisão | E8: Atrasado | F8: Imprensa | G8: Feiras/Eventos | H8: Prospecção ativa | I8: Visita | K8: Revisão/Edição | L8: Comercial | N8: Negociação | O8: 0.75
A9: Infantil | C9: Esgotado | D9: Diagramação | F9: Influenciador | G9: Venda direta | H9: E-mail | I9: Envio de amostra | K9: Diagramação/Capa | L9: Marketing | N9: Fechado - ganho | O9: 1
A10: Juvenil | C10: Fora de catálogo | D10: Capa | F10: Evento/Feira | G10: Governo/Escolas | H10: Evento | I10: Proposta | K10: Royalties | N10: Fechado - perdido | O10: 0
A11: Ensaio | D11: Prova gráfica | F11: Leitor | G11: E-book | K11: Adiantamento autor
A12: Técnico | D12: ISBN/Ficha catalográfica | F12: Fornecedor | K12: Marketing | N12: Probabilidades são estimativas padrão de mercado — ajuste à realidade da editora.
A13: HQ | D13: Gráfica | F13: Autor prospect | K13: Frete/Logística
D14: Distribuição | K14: Eventos
K15: Software/Ferramentas
K16: Impostos
K17: Administrativo
