Workbook

Sheet Como usar
A1: Playbook Comercial LedWave por Nicho
A2: Storytelling, prospecção e argumentação por segmento · apresentações de 10 a 20 minutos · versão 1 (out/2026)
B4: O que é | C4: Material vivo para o time comercial vender painéis de LED por nicho: primeiro vendemos a LedWave (quem somos, tamanho, presença, prova), depois o porquê aquele cliente precisa digitalizar o ponto dele.
B5: Como montar uma apresentação | C5: 1) Abra a aba Gerador de Roteiro. 2) Escolha o nicho e a duração (10, 15 ou 20 min) nas células amarelas. 3) O roteiro sai pronto, bloco a bloco, com tempo, técnica e fala. 4) Ajuste com o nome e os números do cliente.
B6: Antes da reunião | C6: Prospecção Outbound (cadência e script de ligação) → SPIN por Nicho (perguntas inteligentes) → Orçamento por Nicho (o que levantar para orçar certo).
B7: Durante a reunião | C7: Gerador de Roteiro + Escuta Ativa + Objeções. Regra de ouro: na descoberta, o cliente fala 70% do tempo.
B8: Treino do time | C8: Aba Roleplay: cenário, script de referência e ficha de avaliação com nota. Repita com outros nichos trocando a persona.
B9: Como contribuir (gestores) | C9: Toda ideia nova entra na aba Banco de Ideias (uma linha por ideia). Na reunião do time, as ideias com status 'Aprovada' são levadas para a matriz Nichos. A coluna 'Ideias no Banco' da matriz mostra quantas contribuições cada nicho tem.
B10: Células editáveis | C10: Fundo amarelo = campo para preencher ou escolher. Todo o texto das abas de conteúdo também pode ser editado e melhorado. Não apague as colunas A das abas Nichos e Listas: elas alimentam as fórmulas.
B11: Fatos sobre a LedWave | C11: Na aba LedWave – Prova, a coluna Status diz se o dado já tem fonte pública ou se precisa ser validado com a apresentação executiva oficial. Só use em reunião dados 'Fonte pública' ou já validados.
B12: Insights do comercial | C12: As abas Propósitos de Compra, Diferenciais e Cases organizam o que o time comercial trouxe na reunião. Cada nicho da matriz tem os seus propósitos de compra, cases de referência e objeções mais prováveis (colunas T a V). Itens marcados 'Confirmar' precisam de detalhe do comercial antes de ir para o cliente.
B13: Adicionar um nicho | C13: Inclua uma nova linha no fim da matriz Nichos (e nas abas SPIN e Orçamento, com o mesmo nome). Ele aparece automaticamente na lista do Gerador e do Banco de Ideias (até a linha 60).
B15: Legenda | C15: Campo editável / escolha
C16: Cabeçalho de tabela

Sheet Gerador de Roteiro
A1: Gerador de Roteiro
A2: Escolha o nicho e a duração. O roteiro se monta sozinho a partir das outras abas.
A4: Nicho | B4: Farmácias e Drogarias
A5: Duração (min) | B5: 15 | F5: =IF(ISNA(MATCH($B$4,Nichos!$A:$A,0)),"Escolha um nicho da lista","Decisor típico: "&INDEX(Nichos!$B:$B,MATCH($B$4,Nichos!$A:$A,0))) -> Decisor típico: Diretor de Marketing, Diretor de Expansão, Dono da rede, Trade
A6: Cliente (opcional) | B6: Rede Exemplo (38 lojas)
A8: Bloco | B8: Minutos | C8: Termina em (min) | D8: Técnica | E8: Como conduzir | F8: Fala do nicho (pronta para adaptar)
A9: ='Roteiro Mestre'!A4 -> 1. Abertura / Gancho | B9: ='Roteiro Mestre'!B4*$B$5 -> 1.2 | C9: =SUM($B$9:B9) -> 1.2 | D9: ='Roteiro Mestre'!D4 -> Pergunta provocativa (Challenger) + pausa de 3 segundos | E9: ='Roteiro Mestre'!E4 -> Use o GANCHO do nicho. Não comece falando da LedWave. Faça a pergunta, olhe nos olhos e espere a resposta. | F9: =IFERROR("GANCHO: "&INDEX(Nichos!$F:$F,MATCH($B$4,Nichos!$A:$A,0)),"Escolha um nicho da lista") -> GANCHO: Na sua rua existem quantas farmácias? O que faz o cliente escolher a sua antes de ver o preço?
A10: ='Roteiro Mestre'!A5 -> 2. O mundo do cliente (dor) | B10: ='Roteiro Mestre'!B5*$B$5 -> 2.25 | C10: =SUM($B$9:B10) -> 3.45 | D10: ='Roteiro Mestre'!D5 -> SPIN (Situação e Problema) + espelhamento | E10: ='Roteiro Mestre'!E5 -> Descreva a DOR do nicho com as palavras dele. Faça 2 perguntas de descoberta e anote as respostas: elas vão virar números no fechamento. | F10: =IFERROR("DOR: "&INDEX(Nichos!$C:$C,MATCH($B$4,Nichos!$A:$A,0))&CHAR(10)&"PERGUNTE (Situação): "&INDEX('SPIN por Nicho'!$B:$B,MATCH($B$4,'SPIN por Nicho'!$A:$A,0))&CHAR(10)&"PERGUNTE (Problema): "&INDEX('SPIN por Nicho'!$C:$C,MATCH($B$4,'SPIN por Nicho'!$A:$A,0)),"Escolha um nicho da lista") -> DOR: Fachadas parecidas, guerra de preço e um corredor cheio de marcas disputando atenção. A indústria farmacêutica e de dermocosméticos quer visibilidade, mas o espaço é pequeno. PERGUNTE (Situação): Quantas lojas, e quantas abrem por ano? Como funciona a parceria com a indústria hoje? PERGUNTE (Problema): Como vocês se diferenciam das farmácias concorrentes na mesma rua? Campanhas sazonais chegam a tempo em todas as lojas?
A11: ='Roteiro Mestre'!A6 -> 3. Custo da inação | B11: ='Roteiro Mestre'!B6*$B$5 -> 1.5 | C11: =SUM($B$9:B11) -> 4.95 | D11: ='Roteiro Mestre'!D6 -> Ancoragem de perda (aversão à perda) | E11: ='Roteiro Mestre'!E6 -> Use o CUSTO DA INAÇÃO do nicho. Transforme em número com os dados que ele te deu ('se 1 em cada 100 que passam entrasse...'). | F11: =IFERROR("CUSTO DA INAÇÃO: "&INDEX(Nichos!$D:$D,MATCH($B$4,Nichos!$A:$A,0))&CHAR(10)&"PERGUNTE (Implicação): "&INDEX('SPIN por Nicho'!$D:$D,MATCH($B$4,'SPIN por Nicho'!$A:$A,0)),"Escolha um nicho da lista") -> CUSTO DA INAÇÃO: A farmácia da esquina igual a todas as outras perde a decisão de entrada para a que se destaca, e deixa de monetizar o espaço com a indústria. PERGUNTE (Implicação): Se o cliente escolhe a farmácia mais visível, quanto fluxo vocês perdem por ter fachada igual às outras? E quanto a indústria investiria se tivesse onde?
A12: ='Roteiro Mestre'!A7 -> 4. Quem é a LedWave (o guia) | B12: ='Roteiro Mestre'!B7*$B$5 -> 3 | C12: =SUM($B$9:B12) -> 7.95 | D12: ='Roteiro Mestre'!D7 -> StoryBrand (herói x guia) + prova social + regra de 3 | E12: ='Roteiro Mestre'!E7 -> Conte a origem em 20 segundos (R$ 12 mil e Xangai) e escolha 3 provas da aba LedWave – Prova que mais combinam com o nicho. Termine com 'e é por isso que estamos aqui'. | F12: =IFERROR("ORIGEM: "&INDEX('LedWave – Prova'!$C:$C,5)&CHAR(10)&"PROVA 1: "&INDEX('LedWave – Prova'!$C:$C,7)&CHAR(10)&"PROVA 2: "&INDEX('LedWave – Prova'!$C:$C,9)&CHAR(10)&"CASE DE REFERÊNCIA: "&IF(INDEX(Nichos!$U:$U,MATCH($B$4,Nichos!$A:$A,0))="","use o Boulevard.Live (sem case do segmento mapeado)",INDEX(Nichos!$U:$U,MATCH($B$4,Nichos!$A:$A,0)))&CHAR(10)&"Feche com: E é por isso que estamos aqui.","Escolha um nicho da lista") -> ORIGEM: Começamos com R$ 12 mil e uma ideia trazida de Xangai. Hoje somos referência em LED no Brasil. Essa é a prova de que a gente sabe fazer muito com o investimento do cliente. PROVA 1: Quatro anos seguidos entre as empresas que mais crescem no Brasil, número 1 do nosso segmento. Números auditados, não autodeclarados. PROVA 2: Fizemos o maior painel de LED da América Latina. O seu projeto vai receber o mesmo padrão de engenharia. CASE DE REFERÊNCIA: use o Boulevard.Live (sem case do segmento mapeado) Feche com: E é por isso que estamos aqui.
A13: ='Roteiro Mestre'!A8 -> 5. A virada: o porquê (propósito) | B13: ='Roteiro Mestre'!B8*$B$5 -> 1.5 | C13: =SUM($B$9:B13) -> 9.45 | D13: ='Roteiro Mestre'!D8 -> Golden Circle (Por quê → Como → O quê) + analogia | E13: ='Roteiro Mestre'!E8 -> Diga o PROPÓSITO do nicho e conte a HISTÓRIA/ANALOGIA. Feche com a FRASE DE EFEITO e faça uma pausa. | F13: =IFERROR("PROPÓSITO DE COMPRA (descubra qual pesa mais): "&INDEX(Nichos!$T:$T,MATCH($B$4,Nichos!$A:$A,0))&CHAR(10)&"PROPÓSITO: "&INDEX(Nichos!$E:$E,MATCH($B$4,Nichos!$A:$A,0))&CHAR(10)&"HISTÓRIA: "&INDEX(Nichos!$G:$G,MATCH($B$4,Nichos!$A:$A,0))&CHAR(10)&"FRASE DE EFEITO (pausa de 3 s): "&INDEX(Nichos!$K:$K,MATCH($B$4,Nichos!$A:$A,0)),"Escolha um nicho da lista") -> PROPÓSITO DE COMPRA (descubra qual pesa mais): Retail media; Trade; Branding PROPÓSITO: Fazer da farmácia um ponto de saúde e bem-estar que se vê de longe e informa de perto, com mídia paga pela indústria. HISTÓRIA: Cruz verde iluminada foi a primeira tela da farmácia. O painel de LED é a evolução natural dessa cruz: além de dizer 'estou aqui', diz 'tenho o que você precisa hoje'. FRASE DE EFEITO (pausa de 3 s): Farmácia que se vê de longe vende antes do preço.
A14: ='Roteiro Mestre'!A9 -> 6. Como funciona (3 argumentos) | B14: ='Roteiro Mestre'!B9*$B$5 -> 2.55 | C14: =SUM($B$9:B14) -> 12 | D14: ='Roteiro Mestre'!D9 -> Regra de 3 + Feature → Benefício → Ganho | E14: ='Roteiro Mestre'!E9 -> Apresente os 3 argumentos do nicho (Receita, Experiência, Operação), um por slide. Para cada um, diga o ganho em uma frase. Mostre a SOLUÇÃO recomendada e a PROVA/CASE. | F14: =IFERROR("1. RECEITA: "&INDEX(Nichos!$H:$H,MATCH($B$4,Nichos!$A:$A,0))&CHAR(10)&"2. EXPERIÊNCIA: "&INDEX(Nichos!$I:$I,MATCH($B$4,Nichos!$A:$A,0))&CHAR(10)&"3. OPERAÇÃO: "&INDEX(Nichos!$J:$J,MATCH($B$4,Nichos!$A:$A,0))&CHAR(10)&"SOLUÇÃO: "&INDEX(Nichos!$M:$M,MATCH($B$4,Nichos!$A:$A,0)),"Escolha um nicho da lista") -> 1. RECEITA: Monetização com a indústria (dermocosméticos, OTC, higiene) em telas internas; campanhas sazonais (gripe, verão, Dia das Mães) entram no ar na hora. 2. EXPERIÊNCIA: Fachada que se destaca na rua, conteúdo de saúde e prevenção que gera confiança, fila mais leve com conteúdo útil. 3. OPERAÇÃO: Padronização da comunicação em todas as lojas da rede a partir de um único painel de controle. SOLUÇÃO: Painel de fachada, LED de vitrine, telas atrás do balcão e na área de dermocosméticos, rede de retail media.
A15: ='Roteiro Mestre'!A10 -> 7. Objeções antecipadas + números | B15: ='Roteiro Mestre'!B10*$B$5 -> 1.5 | C15: =SUM($B$9:B15) -> 13.5 | D15: ='Roteiro Mestre'!D10 -> Inoculação (antecipar objeção) + Feel/Felt/Found | E15: ='Roteiro Mestre'!E10 -> Traga a OBJEÇÃO nº1 do nicho e a RESPOSTA. Mostre os KPIs que ele vai medir e, se possível, uma conta simples de retorno. | F15: =IFERROR("OBJEÇÃO PROVÁVEL: "&INDEX(Nichos!$P:$P,MATCH($B$4,Nichos!$A:$A,0))&CHAR(10)&"RESPOSTA: "&INDEX(Nichos!$Q:$Q,MATCH($B$4,Nichos!$A:$A,0))&CHAR(10)&"OUTRAS OBJEÇÕES PROVÁVEIS (respostas na aba Objeções): "&INDEX(Nichos!$V:$V,MATCH($B$4,Nichos!$A:$A,0))&CHAR(10)&"O QUE VOCÊ VAI MEDIR: "&INDEX(Nichos!$R:$R,MATCH($B$4,Nichos!$A:$A,0)),"Escolha um nicho da lista") -> OBJEÇÃO PROVÁVEL: A fachada da farmácia tem regras de padronização da rede/franquia. RESPOSTA: Trabalhamos com o manual da marca: o painel vira parte da identidade, não uma exceção a ela. Levamos a proposta pronta para aprovação do franqueador. OUTRAS OBJEÇÕES PROVÁVEIS (respostas na aba Objeções): Política comercial; Gestão de conteúdo; Percepção de valor O QUE VOCÊ VAI MEDIR: Receita de mídia com a indústria, vendas de categorias anunciadas, fluxo de entrada, tempo de rollout de campanha.
A16: ='Roteiro Mestre'!A11 -> 8. Fechamento e próximo passo | B16: ='Roteiro Mestre'!B11*$B$5 -> 1.5 | C16: =SUM($B$9:B16) -> 15 | D16: ='Roteiro Mestre'!D11 -> Peak-End (terminar no ponto alto) + fechamento por próximo passo | E16: ='Roteiro Mestre'!E11 -> Repita a FRASE DE EFEITO, diga a FRASE DE FECHAMENTO e proponha o CTA com data: 'Podemos agendar a visita técnica para quinta ou sexta?' | F16: =IFERROR("PERGUNTE (Necessidade): "&INDEX('SPIN por Nicho'!$E:$E,MATCH($B$4,'SPIN por Nicho'!$A:$A,0))&CHAR(10)&"FRASE: "&INDEX(Nichos!$K:$K,MATCH($B$4,Nichos!$A:$A,0))&CHAR(10)&"FECHAMENTO: "&INDEX(Nichos!$L:$L,MATCH($B$4,Nichos!$A:$A,0))&CHAR(10)&"PRÓXIMO PASSO: "&INDEX(Nichos!$S:$S,MATCH($B$4,Nichos!$A:$A,0)),"Escolha um nicho da lista") -> PERGUNTE (Necessidade): Uma rede de telas que se paga com a indústria e destaca a sua fachada ajudaria na meta deste ano? FRASE: Farmácia que se vê de longe vende antes do preço. FECHAMENTO: A cruz verde chamou o cliente por décadas. Agora é hora de ela conversar com ele. PRÓXIMO PASSO: Simulação de fachada digital com a identidade da rede + proposta de piloto em uma loja âncora.
A17: Total | B17: =SUM(B9:B16) -> 15
A19: Dica: copie a coluna F para as notas do apresentador dos slides. Os tempos vêm dos percentuais da aba Roteiro Mestre.

Sheet Roteiro Mestre
A1: Roteiro Mestre: a estrutura de toda apresentação
A2: Primeiro vendemos a LedWave como guia confiável; depois, o porquê do cliente. Ajuste os percentuais na coluna B (amarelo).
A3: Bloco | B3: % do tempo | C3: Objetivo | D3: Técnica | E3: Como conduzir | F3: Slide sugerido | G3: Erro a evitar
A4: 1. Abertura / Gancho | B4: 0.08 | C4: Capturar atenção nos primeiros 30 a 60 segundos e mostrar que a conversa é sobre o cliente. | D4: Pergunta provocativa (Challenger) + pausa de 3 segundos | E4: Use o GANCHO do nicho. Não comece falando da LedWave. Faça a pergunta, olhe nos olhos e espere a resposta. | F4: Uma imagem forte do mundo do cliente + a pergunta em uma linha. | G4: Começar com 'Bom, a LedWave foi fundada em...'
A5: 2. O mundo do cliente (dor) | B5: 0.15 | C5: Mostrar que entendemos o negócio dele melhor do que ele espera. | D5: SPIN (Situação e Problema) + espelhamento | E5: Descreva a DOR do nicho com as palavras dele. Faça 2 perguntas de descoberta e anote as respostas: elas vão virar números no fechamento. | F5: Antes: a realidade dele (foto do PDV/espaço dele, se possível). | G5: Falar de produto antes de ouvir.
A6: 3. Custo da inação | B6: 0.1 | C6: Criar urgência: ficar parado também custa. | D6: Ancoragem de perda (aversão à perda) | E6: Use o CUSTO DA INAÇÃO do nicho. Transforme em número com os dados que ele te deu ('se 1 em cada 100 que passam entrasse...'). | F6: Um número grande e simples. | G6: Assustar sem dar saída. A saída vem no próximo bloco.
A7: 4. Quem é a LedWave (o guia) | B7: 0.2 | C7: Construir autoridade: o cliente é o herói, a LedWave é o guia que já fez isso antes. | D7: StoryBrand (herói x guia) + prova social + regra de 3 | E7: Conte a origem em 20 segundos (R$ 12 mil e Xangai) e escolha 3 provas da aba LedWave – Prova que mais combinam com o nicho. Termine com 'e é por isso que estamos aqui'. | F7: 3 big numbers + 1 foto de projeto-ícone + logos de clientes do nicho. | G7: Ler a lista inteira de conquistas. Escolha 3.
A8: 5. A virada: o porquê (propósito) | B8: 0.1 | C8: Mudar a conversa de 'comprar uma tela' para 'conquistar um resultado'. | D8: Golden Circle (Por quê → Como → O quê) + analogia | E8: Diga o PROPÓSITO do nicho e conte a HISTÓRIA/ANALOGIA. Feche com a FRASE DE EFEITO e faça uma pausa. | F8: Depois: o mesmo espaço do cliente com o painel (mockup). | G8: Falar de pixel pitch e nits aqui.
A9: 6. Como funciona (3 argumentos) | B9: 0.17 | C9: Dar razões concretas: receita, experiência e operação. | D9: Regra de 3 + Feature → Benefício → Ganho | E9: Apresente os 3 argumentos do nicho (Receita, Experiência, Operação), um por slide. Para cada um, diga o ganho em uma frase. Mostre a SOLUÇÃO recomendada e a PROVA/CASE. | F9: 3 slides, 1 argumento cada, com ícone e uma frase. | G9: Despejar ficha técnica. Ficha técnica vai em anexo.
A10: 7. Objeções antecipadas + números | B10: 0.1 | C10: Responder antes que ele pergunte e mostrar a conta. | D10: Inoculação (antecipar objeção) + Feel/Felt/Found | E10: Traga a OBJEÇÃO nº1 do nicho e a RESPOSTA. Mostre os KPIs que ele vai medir e, se possível, uma conta simples de retorno. | F10: Tabela: investimento x economia x receita nova x KPI. | G10: Discutir desconto antes de mostrar valor.
A11: 8. Fechamento e próximo passo | B11: 0.1 | C11: Sair da reunião com um compromisso concreto, com data. | D11: Peak-End (terminar no ponto alto) + fechamento por próximo passo | E11: Repita a FRASE DE EFEITO, diga a FRASE DE FECHAMENTO e proponha o CTA com data: 'Podemos agendar a visita técnica para quinta ou sexta?' | F11: Frase de efeito em tela cheia + CTA + contato do executivo. | G11: Terminar com 'alguma dúvida?'. Termine com uma escolha entre duas datas.
A12: Total (deve ser 100%) | B12: =SUM(B4:B11) -> 1 | C12: =IF(ROUND(B12,2)=1,"OK","Ajuste os percentuais para somar 100%") -> OK

Sheet LedWave – Prova
A1: LedWave: por que confiar em nós
A2: Use 3 provas por apresentação, escolhidas pelo nicho. Status 'Validar' = conferir com a apresentação executiva antes de usar.
A3: As linhas 5 (Origem), 7 (Reconhecimento) e 9 (Projeto-ícone) alimentam o bloco 4 do Gerador de Roteiro. Ao editar, mantenha essa ordem.
A4: Tema | B4: Fato | C4: Como falar (frase pronta) | D4: Fonte | E4: Status | F4: Observações do gestor
A5: Origem | B5: Fundada em Goiânia no fim de 2010/início de 2011, começou com investimento inicial de R$ 12 mil e uma fábrica SKD. A ideia nasceu em uma viagem do fundador e CEO Tiago Brito a Xangai. | C5: Começamos com R$ 12 mil e uma ideia trazida de Xangai. Hoje somos referência em LED no Brasil. Essa é a prova de que a gente sabe fazer muito com o investimento do cliente. | D5: Exame: 'Negócio de R$ 12 mil vira líder em LED e hoje fatura R$ 200 milhões'; Marcas pelo Mundo (entrevista Tiago Brito) | E5: Fonte pública
A6: Tamanho | B6: Faturamento anual na casa de R$ 200 milhões (aproximado). | C6: Uma operação de cerca de R$ 200 milhões por ano. Você não está comprando de uma startup; está comprando de quem lidera o setor. | D6: Exame (reportagem citada acima) | E6: Validar
A7: Reconhecimento | B7: 4 anos consecutivos no ranking Exame Negócios em Expansão. Em 2025: 1ª colocada no segmento de painéis de LED e 70ª na faixa de R$ 30 a 150 milhões, com dados auditados pela PwC. | C7: Quatro anos seguidos entre as empresas que mais crescem no Brasil, número 1 do nosso segmento. Números auditados, não autodeclarados. | D7: Curta Mais; Jornal do Brás; Folha Vitória (ranking Exame) | E7: Fonte pública
A8: Presença | B8: Sede e linha de produção em Goiânia; unidades em São Paulo, Brasília e Orlando (EUA); operações no Brasil, Estados Unidos e China. | C8: Fabricamos no Brasil, operamos nos Estados Unidos e temos pé na China, onde está a tecnologia de LED. Isso significa preço, prazo e suporte. | D8: Site LedWave (página institucional); Exame | E8: Fonte pública
A9: Projeto-ícone | B9: Boulevard.Live, em Brasília: 1.125 m², o maior painel de LED da América Latina, inspirado na Times Square. | C9: Fizemos o maior painel de LED da América Latina. O seu projeto vai receber o mesmo padrão de engenharia. | D9: Blog LedWave (Boulevard.Live); Inviron | E9: Fonte pública
A10: Internacional | B10: Única empresa brasileira de LED com estande próprio na NRF 2026 (Nova York), maior feira de varejo do mundo. | C10: Na maior feira de varejo do mundo, só uma empresa brasileira de LED tinha estande próprio: a LedWave. | D10: Agência Logística; Portal Sala da Notícia | E10: Fonte pública
A11: Ecossistema | B11: Parceira oficial da ABF Expo; presença em APAS, Abrasel, ExpoPostos, SuperAgos, Fóruns SA+, Expo Cristã. | C11: Estamos onde os maiores varejistas e franqueadores do país se encontram. | D11: ABC da Comunicação (ABF Expo); plano de eventos 2026/2 (Drive) | E11: Fonte pública
A12: Mercado | B12: Circuito LedWave da Copa elevou a demanda por painéis de LED em 50%. | C12: Quando o Brasil inteiro olha para uma tela, muitas vezes é uma tela LedWave. | D12: Jornal do Brás | E12: Fonte pública
A13: Investimento | B13: Plano de investimento de R$ 40 milhões e expansão para os EUA. | C13: Estamos investindo pesado em capacidade e tecnologia. Você compra hoje de quem vai estar aqui amanhã para dar suporte. | D13: Inviron | E13: Validar
A14: Propósito | B14: Conexão com o Sistema B (sustentabilidade no DNA da mídia digital). | C14: Crescer com responsabilidade faz parte de quem somos. | D14: AdNews: 'LedWave e o Sistema B' | E14: Validar
A15: Solução completa | B15: Fabricação, venda, locação, instalação, conteúdo, gestão e retail media. Parceria WeOOH ('Duas potências. Uma nova força'). | C15: Não vendemos painel. Entregamos o resultado que o painel gera, do projeto ao conteúdo. | D15: Apresentação Retail Media (Drive); Convenção de Vendas 2026 | E15: Validar
A16: Conteúdo e autoridade | B16: LedCast (podcast com líderes do varejo, ex.: Shop! Brasil, Farmelhor, Buddha Spa) e quadro RADAR LEDWAVE. | C16: A gente conversa com quem decide o varejo no Brasil e traz esse conhecimento para o seu projeto. | D16: Calendário editorial (Drive); imprensa | E16: Fonte pública
... A18: Números da apresentação executiva | B18: [Preencher: m² instalados, nº de projetos, nº de clientes, garantia, prazo de assistência, principais logos] | C18: [Preencher] | D18: Apresentação executiva LedWave | E18: Validar

Sheet Propósitos de Compra
A1: Propósitos de compra: por que o cliente compra
A2: Insight do time comercial. Descubra na conversa qual propósito pesa mais e conduza a apresentação por ele.
A3: Propósito | B3: O que o cliente quer de verdade | C3: Pergunta para identificar | D3: Resultados esperados ligados | E3: Nichos onde mais aparece | F3: Observações do gestor
A4: Mídia | B4: Vender espaço na tela para anunciantes e transformar o painel em fonte de receita. | C4: Você pensa em vender espaço na tela para outras marcas? | D4: Monetização; aumento de receita; impacto | E4: Postos de Combustível e Conveniência; DOOH e Investidores de Mídia; Shopping Centers; Arenas, Estádios, Academias e Esportes; Poder Público e Mobiliário Urbano
A5: Eficiência operacional | B5: Trocar impressos, reduzir retrabalho e atualizar a comunicação de várias unidades de um só lugar. | C5: Quanto tempo e dinheiro a sua equipe gasta hoje para trocar a comunicação? | D5: Eficiência ops; economia; dinamismo; facilidade técnica | E5: Supermercados, Atacarejos e Home Centers; Postos de Combustível e Conveniência; Franquias e Redes; Bares, Restaurantes e Food Service; Saúde (Hospitais, Clínicas e Laboratórios)
A6: Branding | B6: Fortalecer a marca e ser lembrado: a tela como assinatura visual da empresa. | C6: O que você quer que as pessoas lembrem da sua marca quando passam por aqui? | D6: Empoderamento da mensagem; modernidade; diferencial competitivo | E6: Varejo de Moda e Vitrines; Farmácias e Drogarias; Postos de Combustível e Conveniência; Concessionárias de Veículos; Franquias e Redes; Corporativo (Comunicação Interna e Recepções); Saúde (Hospitais, Clínicas e Laboratórios)
A7: Retrofit / arquitetura | B7: Modernizar fachadas, halls e prédios, integrando o LED ao projeto arquitetônico. | C7: Existe uma reforma ou um projeto de arquitetura em andamento? | D7: Beleza; modernidade; longevidade; qualidade | E7: DOOH e Investidores de Mídia; Construtoras e Stands de Vendas; Corporativo (Comunicação Interna e Recepções); Poder Público e Mobiliário Urbano
A8: Retail media | B8: Fazer do ponto de venda um canal de mídia vendido para a indústria. | C8: A indústria já paga por exposição nas suas lojas? Ela pede comprovação? | D8: Monetização; aumento do fluxo no PDV; aumento de receita | E8: Supermercados, Atacarejos e Home Centers; Farmácias e Drogarias
A9: Trade | B9: Executar e comprovar as ações de trade marketing no PDV, no tempo certo. | C9: Como as campanhas de trade chegam às lojas hoje, e como você comprova a execução? | D9: Aumento do fluxo no PDV; dinamismo; eficiência ops | E9: Varejo de Moda e Vitrines; Supermercados, Atacarejos e Home Centers; Farmácias e Drogarias; Franquias e Redes
A10: Insumo de trabalho | B10: Usar o painel como ferramenta do dia a dia: palco, culto, aula, transmissão, evento. | C10: Com que frequência você precisa de tela para trabalhar (eventos, cultos, aulas, transmissões)? | D10: Disponibilidade física; equipe técnica; garantia; facilidade técnica | E10: Igrejas e Centros Religiosos; Eventos, Agências e Produtoras; Educação (Escolas, Faculdades e Universidades)
A11: Experiência | B11: Encantar o cliente, o visitante ou o colaborador e fazer o espaço ser lembrado. | C11: O que você quer que as pessoas sintam quando entram aqui? | D11: Impacto; fidelização; realização; inovação | E11: Varejo de Moda e Vitrines; Shopping Centers; Concessionárias de Veículos; Construtoras e Stands de Vendas; Bares, Restaurantes e Food Service; Igrejas e Centros Religiosos; Hotéis, Parques, Clubes e Piscinas; Eventos, Agências e Produtoras; Educação (Escolas, Faculdades e Universidades); Saúde (Hospitais, Clínicas e Laboratórios); Arenas, Estádios, Academias e Esportes; Poder Público e Mobiliário Urbano
A12: Entretenimento | B12: Atrair e reter público com conteúdo, shows, jogos e atrações. | C12: Que tipo de atração faria o seu público voltar mais vezes? | D12: Fidelização; impacto; aumento de receita; exclusividade | E12: Shopping Centers; Bares, Restaurantes e Food Service; Igrejas e Centros Religiosos; Hotéis, Parques, Clubes e Piscinas; Eventos, Agências e Produtoras; Arenas, Estádios, Academias e Esportes
A13: Status | B13: Ter o painel mais impressionante, a referência da cidade ou do setor. | C13: Que projeto de LED você viu e pensou: eu quero isso para nós? | D13: Exclusividade; diferencial competitivo; inovação; realização | E13: DOOH e Investidores de Mídia; Concessionárias de Veículos; Construtoras e Stands de Vendas; Hotéis, Parques, Clubes e Piscinas; Corporativo (Comunicação Interna e Recepções); Educação (Escolas, Faculdades e Universidades)
A15: Resultados esperados (lista do comercial)
A16: Beleza | B16: Monetização | C16: Impacto
A17: Empoderamento da mensagem | B17: Modernidade | C17: Eficiência ops
A18: Disponibilidade física | B18: Garantia | C18: Equipe técnica
A19: Longevidade | B19: Economia | C19: Aumento de receita
A20: Fidelização | B20: Dinamismo | C20: Aumento do fluxo no PDV
A21: Facilidade técnica | B21: Realização | C21: Inovação
A22: Exclusividade | B22: Qualidade | C22: Diferencial competitivo

Sheet Diferenciais
A1: Diferenciais da LedWave
A2: Insight do time comercial. Use 3 a 5 por apresentação, escolhidos pelo propósito de compra do cliente. 'Confirmar' = validar o texto com o comercial antes de usar com cliente.
A3: Diferencial | B3: Como falar para o cliente | C3: Prova / o que levar | D3: Status | E3: Observações do gestor
A4: Joint venture | B4: Somamos forças com parceiros de mídia para entregar não só a tela, mas o negócio de mídia por trás dela. | C4: Nome e escopo da joint venture (ex.: WeOOH?) | D4: Confirmar
A5: Modelo comercial | B5: Montamos o modelo que cabe no seu negócio: compra, locação, mídia compartilhada ou combinações. | C5: Tabela de modelos comerciais | D5: Confirmar
A6: Locação / venda | B6: Você escolhe: comprar, alugar ou começar alugando e depois comprar. | C6: Comparativo compra x locação | D6: OK
A7: Capilaridade de atendimento | B7: Atendemos o Brasil inteiro a partir de Goiânia, São Paulo e Brasília, e os EUA por Orlando. | C7: Mapa de atendimento e equipes | D7: OK
A8: Estoque | B8: Temos estoque próprio: menos espera entre a assinatura e a tela acesa. | C8: Prazo médio de entrega | D8: Confirmar prazos
A9: Acervo | B9: Um acervo amplo de modelos e formatos para cada aplicação: indoor, outdoor, curvo, transparente, piso. | C9: Catálogo de produtos / acervo de locação | D9: Confirmar significado
A10: Tempo de vida | B10: Mais de 15 anos de mercado e painéis feitos para durar. | C10: Ano de fundação + vida útil dos painéis | D10: Confirmar significado
A11: Know-how | B11: Mais de 15 anos fabricando, instalando e operando painéis de LED: sabemos o que funciona em cada tipo de espaço, do PDV ao maior painel da América Latina. | C11: Histórico de projetos + Boulevard.Live | D11: OK
A12: Prova social | B12: Marcas como Nordestão, Rosewood, Beto Carrero World e Museu do Amanhã escolheram a LedWave. | C12: Cases e depoimentos | D12: OK
A13: Única fábrica | B13: Fabricamos no Brasil, com linha de produção própria em Goiânia. | C13: Confirmar se é a única fábrica do Brasil antes de dizer 'única' | D13: Confirmar
A14: Certificações | B14: Produtos certificados e processos dentro das normas. | C14: Lista de certificações | D14: Confirmar lista
A15: Pioneira | B15: Fomos pioneiros em trazer a fabricação de painéis de LED para o Brasil. | C15: Histórico 2010/2011 | D15: Confirmar
... A22: Premiações | B22: Quatro anos seguidos no ranking Exame das empresas que mais crescem. | C22: Ranking Exame + outros prêmios | D22: Confirmar outros prêmios

Sheet Cases
A1: Cases de referência
A2: Cases citados pelo time comercial. Preencha desafio, entrega e resultado: é isso que entra nas apresentações.
A3: Case | B3: Segmento (nicho) | C3: Propósitos de compra | D3: Desafio do cliente | E3: O que a LedWave entregou | F3: Resultado (número, se houver) | G3: Fotos/vídeo (link) | H3: Autorizado para uso com clientes? | I3: Status
A4: Nordestão | B4: Supermercados, Atacarejos e Home Centers | C4: Retail media; Trade; Eficiência operacional | I4: Detalhar
A5: Animalia | B5: Hotéis, Parques, Clubes e Piscinas | C5: Entretenimento; Experiência | I5: Confirmar segmento e detalhar
A6: Rosewood | B6: Hotéis, Parques, Clubes e Piscinas | C6: Status; Experiência; Retrofit / arquitetura | I6: Detalhar
A7: Beto Carrero World | B7: Hotéis, Parques, Clubes e Piscinas | C7: Entretenimento; Experiência | I7: Detalhar
A8: Cestto | B8: [Confirmar segmento] | I8: Confirmar
A9: Museu do Amanhã | B9: Poder Público e Mobiliário Urbano | C9: Experiência; Retrofit / arquitetura | I9: Detalhar

Sheet Nichos
A1: Matriz de Nichos: o porquê de cada cliente
A2: Uma linha por nicho. É a fonte do Gerador de Roteiro. Melhore à vontade; registre a mudança na coluna 'Última contribuição'.
A3: Nicho | B3: Decisor típico | C3: Dor principal (o mundo dele hoje) | D3: Custo da inação | E3: Propósito (o porquê) | F3: Gancho de abertura | G3: História / analogia | H3: Argumento 1: Receita | I3: Argumento 2: Experiência e marca | J3: Argumento 3: Operação e custo | K3: Frase de efeito | L3: Frase de fechamento | M3: Solução recomendada | N3: Prova / case (a completar) | O3: Perguntas de descoberta | P3: Objeção nº 1 | Q3: Resposta à objeção | R3: KPIs que o cliente vai medir | S3: Próximo passo (CTA) | T3: Propósitos de compra (comercial) | U3: Cases de referência | V3: Objeções mais prováveis (comercial) | W3: Ideias no Banco | X3: Última contribuição (gestor/data) | Y3: Notas
A4: Varejo de Moda e Vitrines | B4: Dono da rede, Diretor de Marketing, Gerente de Visual Merchandising | C4: A vitrine é estática: a coleção muda, a promoção muda, mas a fachada fala a mesma coisa por semanas. Cada troca exige gráfica, instalação e prazo. | D4: Cada dia com vitrine parada é fluxo de calçada que passa reto. Quem não para na vitrine não entra na loja. | E4: Transformar a vitrine em um vendedor que trabalha 24h, chama o cliente pelo movimento e conta a história da coleção antes de ele entrar. | F4: Quantas pessoas passam na frente da sua loja por dia? Agora, quantas param? A diferença entre esses dois números é o tamanho da oportunidade que estamos aqui para discutir. | G4: Antes x depois: a mesma vitrine com um banner de liquidação desbotado e, ao lado, a coleção nova em movimento, com troca de conteúdo do celular em minutos. O olho humano é programado para seguir movimento. | H4: Mais paradas na vitrine geram mais entradas na loja; promoções relâmpago (horário de almoço, fim de tarde) entram no ar na hora, sem gráfica. | I4: A marca passa a ter cara de flagship: a loja de rua ou de shopping conversa com o padrão das grandes marcas internacionais. | J4: Fim do custo recorrente de impressão e instalação a cada coleção; gestão centralizada do conteúdo para todas as lojas da rede. | K4: Vitrine parada é vendedor dormindo. | L4: A coleção nova merece uma vitrine à altura. Vamos colocar a sua loja para falar com quem passa? | M4: Painel de vitrine de alto brilho, LED transparente para fachadas de vidro, totens digitais internos, gestão de conteúdo em rede. | N4: Cases de varejo da LedWave (ver aba LedWave – Prova; inserir case de moda específico). Briefing Torra (Drive) como referência de proposta. | O4: Quanto você gasta por coleção com impressos? Quanto tempo leva entre decidir uma promoção e ela estar na vitrine? Como você mede o fluxo que para na frente da loja hoje? | P4: Painel de LED é caro para uma loja só. | Q4: Compare com o custo de 12 meses de impressos, instalação e mídia local. O painel substitui esses custos e ainda fica com você. Podemos montar a conta juntos agora. | R4: Taxa de parada na vitrine, entrada em loja, vendas da peça anunciada, economia com impressos. | S4: Agendar visita técnica para medir a vitrine e simular o conteúdo da próxima coleção no painel. | T4: Branding; Experiência; Trade | V4: Preço; Gestão de conteúdo; Percepção de valor | W4: =COUNTIF('Banco de Ideias'!$C:$C,A4) -> 0
A5: Supermercados, Atacarejos e Home Centers | B5: Diretor Comercial, Diretor de Trade Marketing, Gerente de Marketing, Operações | C5: Oferta muda todo dia, cartaz de papel não acompanha. O trade da indústria paga por espaço, mas o impresso não mede nada e envelhece rápido. | D5: O varejista deixa de vender mídia dentro da própria loja, enquanto o retail media cresce no Brasil (R$ 4,8 bi em 2025, +37%, IAB Brasil/Kantar). | E5: Transformar a loja em canal de mídia: a tela deixa de ser custo e passa a gerar receita com as marcas que já estão nas gôndolas. | F5: Se 80% a 90% das vendas do varejo ainda acontecem na loja física, por que quase toda a verba de mídia está fora dela? | G5: Referência Walmart Connect: a loja virou canal de mídia e a publicidade virou uma linha de receita bilionária. A lição é simples: a loja física também é mídia, e mídia gera receita. | H5: Retail media: venda de espaço nas telas para a indústria, com margem potencial de 70% a 90% (McKinsey). A tela se paga com a verba de trade. | I5: Ofertas e receitas em movimento no momento da decisão; comunicação mais moderna que a da concorrência no mesmo bairro. | J5: Troca de preços e ofertas em tempo real por loja, sem impressão, sem retrabalho, com prova de veiculação para o fornecedor. | K5: Sua loja já tem audiência. Falta transformar audiência em receita. | L5: A pergunta não é se o seu PDV vai virar mídia. É quem vai fazer isso primeiro na sua praça. | M5: Telas de checkout, ponta de gôndola, painéis de entrada e fachada, retail media com gestão de conteúdo e relatório de veiculação (parceria WeOOH a validar). | N5: Big numbers de retail media (doc Retail Media no PDV). Participação em eventos APAS, Rede Brasil, SuperAgos. Inserir case de supermercado. | O5: Quanto da sua verba de trade hoje vira impresso? Seus fornecedores pedem prova de exposição? Você já pensou em vender mídia dentro da loja? | P5: Não tenho equipe para gerenciar conteúdo e vender mídia. | Q5: Por isso a LedWave entrega a solução completa: tela, gestão de conteúdo e modelo de negócio. Você cuida da loja, nós ajudamos a operar a mídia. | R5: Receita de mídia por loja, sell-out do produto anunciado, economia com impressos, tempo de troca de oferta. | S5: Workshop de 1h para desenhar o piloto de retail media em 1 a 3 lojas. | T5: Retail media; Trade; Eficiência operacional | U5: Nordestão | V5: Gestão de conteúdo; Aprovação por financeiro; Momento financeiro | W5: =COUNTIF('Banco de Ideias'!$C:$C,A5) -> 0
A6: Farmácias e Drogarias | B6: Diretor de Marketing, Diretor de Expansão, Dono da rede, Trade | C6: Fachadas parecidas, guerra de preço e um corredor cheio de marcas disputando atenção. A indústria farmacêutica e de dermocosméticos quer visibilidade, mas o espaço é pequeno. | D6: A farmácia da esquina igual a todas as outras perde a decisão de entrada para a que se destaca, e deixa de monetizar o espaço com a indústria. | E6: Fazer da farmácia um ponto de saúde e bem-estar que se vê de longe e informa de perto, com mídia paga pela indústria. | F6: Na sua rua existem quantas farmácias? O que faz o cliente escolher a sua antes de ver o preço? | G6: Cruz verde iluminada foi a primeira tela da farmácia. O painel de LED é a evolução natural dessa cruz: além de dizer 'estou aqui', diz 'tenho o que você precisa hoje'. | H6: Monetização com a indústria (dermocosméticos, OTC, higiene) em telas internas; campanhas sazonais (gripe, verão, Dia das Mães) entram no ar na hora. | I6: Fachada que se destaca na rua, conteúdo de saúde e prevenção que gera confiança, fila mais leve com conteúdo útil. | J6: Padronização da comunicação em todas as lojas da rede a partir de um único painel de controle. | K6: Farmácia que se vê de longe vende antes do preço. | L6: A cruz verde chamou o cliente por décadas. Agora é hora de ela conversar com ele. | M6: Painel de fachada, LED de vitrine, telas atrás do balcão e na área de dermocosméticos, rede de retail media. | N6: LedCast com Farmelhor (pílula pós-ABF). Participação na Abrafarma. Validar case de rede. | O6: A indústria já paga por exposição nas suas lojas? Como você comunica campanhas sazonais hoje? Quanto tempo leva para padronizar uma campanha em todas as lojas? | P6: A fachada da farmácia tem regras de padronização da rede/franquia. | Q6: Trabalhamos com o manual da marca: o painel vira parte da identidade, não uma exceção a ela. Levamos a proposta pronta para aprovação do franqueador. | R6: Receita de mídia com a indústria, vendas de categorias anunciadas, fluxo de entrada, tempo de rollout de campanha. | S6: Simulação de fachada digital com a identidade da rede + proposta de piloto em uma loja âncora. | T6: Retail media; Trade; Branding | V6: Política comercial; Gestão de conteúdo; Percepção de valor | W6: =COUNTIF('Banco de Ideias'!$C:$C,A6) -> 1
A7: Postos de Combustível e Conveniência | B7: Proprietário do posto/rede, Diretor Comercial de distribuidora, Gerente de conveniência | C7: O preço na placa é a única comunicação, e o cliente decide em segundos, a 60 km/h. A loja de conveniência é invisível da pista. | D7: O motorista que passa reto não volta. A margem do combustível é apertada e a conveniência, que tem margem, não é vista. | E7: Fazer o posto ser visto, escolhido e lembrado, e transformar a rodovia em audiência paga. | F7: Seu cliente decide se entra no seu posto em menos de cinco segundos. O que ele vê nesses cinco segundos? | G7: Duas placas na estrada à noite: uma de preço fixo, apagada; outra com preço, promoção de café + pão de queijo e a marca em movimento. Qual delas faz o motorista dar seta? | H7: Mídia DOOH para anunciantes locais e regionais na pista; promoções da conveniência e serviços (lavagem, troca de óleo) que aumentam ticket. | I7: Posto moderno, iluminado e seguro à noite, percepção de marca forte na rodovia. | J7: Atualização de preço remota e instantânea, sem subir em escada, com conteúdo programado por horário. | K7: Na estrada, quem não é visto não é abastecido. | L7: Seu posto já tem o fluxo. Vamos fazer esse fluxo parar? | M7: Totem de preços em LED outdoor (alto brilho, IP65), painel de testeira, telas na bomba e na conveniência, mídia DOOH. | N7: Participação na ExpoPostos. ICP 1 (Investidor de Mídia / Postos). Inserir case de posto. | O7: Quantos veículos passam na sua frente por dia? Qual a participação da conveniência no seu lucro? Anunciantes locais já te procuraram? | P7: Meu cliente só olha preço. | Q7: Exatamente: e o painel mostra o preço melhor, mais longe e mais rápido. O que vem depois do preço (café, lavagem, mídia) é margem extra que hoje você não captura. | R7: Veículos que entram x fluxo da pista, ticket da conveniência, receita de mídia DOOH. | S7: Estudo de visibilidade da pista (distância, ângulo, fluxo) e proposta de totem + testeira. | T7: Mídia; Eficiência operacional; Branding | V7: Política local / licenças; Fabricação de estrutura metálica; Consumo de energia | W7: =COUNTIF('Banco de Ideias'!$C:$C,A7) -> 0
A8: DOOH e Investidores de Mídia | B8: Investidor, CEO/Proprietário de exibidora, Diretor Comercial de mídia | C8: Quer entrar ou crescer em mídia exterior digital, mas precisa de ativo confiável, ponto bem escolhido e retorno previsível. | D8: Os melhores pontos da cidade estão sendo ocupados agora. Ponto bom não espera. | E8: Construir um ativo de mídia que gera receita recorrente por anos, com um fabricante que sabe operar mídia porque também opera. | F8: Um painel de LED não é um custo, é um imóvel que paga aluguel em inserções. A pergunta é: quanto rende o seu metro quadrado? | G8: Boulevard.Live, em Brasília: 1.125 m², o maior painel de LED da América Latina, pensado no ponto de maior fluxo de pessoas e veículos da cidade. A LedWave não só vende painel; ela sabe o que faz um painel faturar. | H8: Receita recorrente por inserção, programática e anunciante local; o DOOH já soma R$ 4,4 bi no Brasil (IAB Brasil/Kantar, 2025). | I8: Ponto icônico vira referência da cidade e atrai anunciantes premium. | J8: Fabricação própria, assistência técnica, alto brilho e durabilidade outdoor reduzem tempo de tela apagada (que é receita perdida). | K8: Painel apagado é aluguel perdido. Escolha quem mantém sua tela no ar. | L8: Vamos escolher juntos o seu próximo ponto e colocar a conta no papel? | M8: Painéis outdoor de grande formato, empenas, frontlights digitais, mobiliário urbano, gestão de conteúdo e programação. | N8: Boulevard.Live (1.125 m²); HighLine – Edifício Baracat (Brasília); WE SUPER OOH; parceria WeOOH (validar). | O8: Quantos pontos você opera hoje? Qual ocupação média? Quanto tempo de tela apagada você teve no último ano? Já tem anunciantes âncora? | P8: O payback é longo e o risco é alto. | Q8: Por isso o projeto começa pelo ponto, não pelo painel: fluxo, visibilidade, licenciamento e plano comercial. Com fabricante que também opera mídia, o risco técnico cai. | R8: Ocupação, receita por m², uptime da tela, payback do ponto. | S8: Estudo de ponto + simulação de payback com cenário conservador, base e otimista. | T8: Mídia; Status; Retrofit / arquitetura | V8: Política local / licenças; SLA; Crédito | W8: =COUNTIF('Banco de Ideias'!$C:$C,A8) -> 0
A9: Shopping Centers | B9: Superintendente, Gerente de Marketing, Gerente Comercial / Mall & Media | C9: O shopping disputa visita com o e-commerce e precisa ser destino. O mall media tradicional é estático e difícil de vender. | D9: Sem experiência, o shopping vira corredor de passagem; e o espaço de mídia que poderia faturar fica vazio. | E9: Transformar o shopping em palco: experiências que geram visita, fotos, redes sociais e receita de mídia. | F9: Qual foi a última coisa no seu shopping que fez alguém parar, tirar o celular do bolso e filmar? | G9: As grandes capitais têm seus pontos de LED que viram cartão-postal. Uma tela anamórfica 3D na praça de eventos faz o shopping aparecer nas redes de milhares de pessoas, de graça. | H9: Mall media digital vendido para lojistas e marcas nacionais; ativações e eventos com patrocínio. | I9: Experiências instagramáveis, datas comemorativas e eventos que aumentam fluxo e permanência. | J9: Sinalização e wayfinding digitais, comunicação com lojistas e campanhas atualizadas em minutos. | K9: Shopping sem experiência é só um estacionamento com lojas. | L9: Vamos criar o ponto do seu shopping que todo mundo quer filmar? | M9: Painéis de praça de eventos, LED anamórfico/3D, empenas e fachadas, totens, mall media em rede. | N9: Relacionamento com Ancar / FFX (NRF 2027). Inserir case de shopping. | O9: Como está a receita de mall media hoje? Quais datas trazem mais fluxo? Os lojistas pedem mais visibilidade? | P9: Já temos TVs espalhadas pelo mall. | Q9: TV comunica; LED de grande formato encanta. Escala, brilho e formato livre criam momentos que uma TV não cria, e é isso que vende mídia premium. | R9: Fluxo de visitantes, permanência, receita de mall media, menções nas redes. | S9: Proposta de experiência-âncora para a próxima data forte (Natal, Dia das Mães) + plano de mall media. | T9: Experiência; Entretenimento; Mídia | V9: Aprovação por financeiro; Concorrência; Percepção de valor | W9: =COUNTIF('Banco de Ideias'!$C:$C,A9) -> 0
A10: Concessionárias de Veículos | B10: Dono do grupo, Gerente Geral, Gerente de Marketing da concessionária | C10: Showroom com carros parados e banners genéricos da montadora. O cliente chega já pesquisado na internet e o showroom não acrescenta emoção. | D10: Venda de alto ticket é emoção. Showroom frio perde o cliente para a loja que faz ele imaginar o carro na estrada. | E10: Levar a estrada para dentro do showroom: fazer o cliente sentir o carro antes do test-drive. | F10: Seu cliente já viu o carro no site. O que o seu showroom mostra que o site não mostra? | G10: Lançamento: luzes apagam, o painel atrás do carro mostra a serra, a chuva, a família viajando, e o carro real está ali na frente. Isso é cenografia que vende. | H10: Mais conversão no showroom, eventos de lançamento que geram leads e cofinanciamento de ações com a montadora. | I10: Showroom premium alinhado ao padrão global das marcas; experiência que justifica o preço. | J10: Conteúdo da montadora, condições e estoque atualizados em tempo real; fachada que comunica ofertas para a avenida. | K10: Carro se compra com o coração e se justifica com a razão. O painel fala com os dois. | L10: Vamos fazer o seu próximo lançamento ser lembrado? | M10: Painel de fundo de showroom, LED de fachada, totens de ofertas, painel para eventos e lançamentos (venda ou locação). | N10: ICP 3 (Branding & Experiência). Inserir case de concessionária. | O10: Quantos lançamentos vocês têm por ano? A montadora co-investe em ações de PDV? Quanto vocês gastam em eventos de lançamento? | P10: A montadora define o padrão do showroom. | Q10: O painel recebe o conteúdo oficial da montadora e respeita o padrão visual. Podemos apresentar a proposta junto à regional da marca. | R10: Conversão de visita em venda, leads de eventos, tempo de permanência no showroom. | S10: Demonstração no showroom LedWave com conteúdo da marca do cliente. | T10: Status; Experiência; Branding | V10: Preço; Momento financeiro; Gestão de conteúdo | W10: =COUNTIF('Banco de Ideias'!$C:$C,A10) -> 0
A11: Construtoras e Stands de Vendas | B11: Diretor de Incorporação, Diretor de Marketing, Gerente de Vendas imobiliárias | C11: Vender na planta é vender algo que não existe. Maquete e perspectivas impressas não fazem o cliente se imaginar morando lá. | D11: Cada visita ao stand que sai sem emoção é uma unidade que vai para o concorrente. Ciclo de venda mais longo é custo financeiro. | E11: Fazer o cliente viver o empreendimento antes de ele existir. | F11: Seu cliente está comprando um sonho que ainda é um terreno. Como ele enxerga esse sonho hoje no seu stand? | G11: Visitante entra no stand, o painel abre a vista do 20º andar ao pôr do sol, depois a área de lazer com as crianças na piscina. Ele não vê uma planta; ele vê a vida dele. | H11: Vendas mais rápidas no lançamento; o painel acompanha os próximos empreendimentos (reaproveitamento entre stands). | I11: Stand com padrão de alto luxo, coerente com o ticket do imóvel; tapume digital que vira mídia na obra. | J11: Atualização de tabela, unidades disponíveis e condições em tempo real; locação para stands temporários. | K11: Ninguém compra metro quadrado. Compra o futuro que cabe nele. | L11: Vamos fazer o seu próximo lançamento ser visto antes de ser construído? | M11: Painel imersivo no stand, LED em tapume de obra, fachada do stand, locação para lançamentos. | N11: Artigo 'Painel de LED em estandes de construtoras' (calendário editorial). Inserir case. | O11: Quantos lançamentos estão previstos? Qual o VGV do próximo? Quanto tempo dura um stand? Vocês reaproveitam estrutura? | P11: O stand é temporário, não compensa comprar. | Q11: Temos locação e também compra com reaproveitamento: o mesmo painel vai do stand para o próximo lançamento ou para o hall do prédio entregue. | R11: Velocidade de vendas (unidades/mês), conversão de visita em proposta, custo de stand por unidade vendida. | S11: Apresentar conceito imersivo para o próximo lançamento + comparativo compra x locação. | T11: Status; Retrofit / arquitetura; Experiência | V11: Forma de pagamento; Fabricação de estrutura metálica; Preço | W11: =COUNTIF('Banco de Ideias'!$C:$C,A11) -> 0
A12: Franquias e Redes | B12: Franqueador (CEO, Diretor de Expansão, Marketing), franqueados master | C12: Garantir que a marca seja a mesma em 50, 200, 1.000 lojas. Campanhas chegam atrasadas, impressos são aplicados errado, cada franqueado faz de um jeito. | D12: Marca inconsistente perde valor e o franqueado perde venda; cada campanha impressa é custo multiplicado pelo número de lojas. | E12: Dar ao franqueador o controle da marca em todas as lojas e ao franqueado uma loja que vende mais. | F12: Se hoje você lança uma campanha nacional às 9h, a que horas ela está na última loja da rede? | G12: Rede com campanha de Dia dos Pais: com impresso, chega em semanas e cada loja aplica de um jeito; com LED em rede, um clique na central e todas as lojas do Brasil estão iguais no mesmo minuto. | H12: Campanhas no tempo certo vendem mais; padronização aumenta o ticket e a percepção de valor da marca. | I12: Experiência idêntica em qualquer cidade, fator de atração para novos franqueados. | J12: Gestão centralizada de conteúdo, kit padrão de tela para novas unidades, fim da logística de impressos. | K12: Uma marca, mil lojas, um clique. | L12: Vamos colocar o padrão LedWave no seu kit de abertura de loja? | M12: Kit de LED padrão por formato de loja, menu boards, vitrine digital, gestão de conteúdo em rede. | N12: Parceira da ABF Expo; LedCast com Buddha Spa e Farmelhor; Convenção ABF do Franchising. | O12: Quantas lojas e quantas aberturas previstas no ano? Quanto custa uma campanha impressa para toda a rede? Quem paga, franqueador ou franqueado? | P12: O franqueado não vai querer pagar. | Q12: Mostramos ao franqueado a conta: economia de impressos + venda adicional. E temos modelos de financiamento e de kit de abertura que diluem o investimento. | R12: Tempo de rollout de campanha, aderência ao padrão, vendas por loja, custo de comunicação por unidade. | S12: Projeto de kit padrão para o modelo de loja do cliente + piloto em lojas próprias. | T12: Branding; Eficiência operacional; Trade | V12: Forma de pagamento; Crédito; Gestão de conteúdo | W12: =COUNTIF('Banco de Ideias'!$C:$C,A12) -> 0
A13: Bares, Restaurantes e Food Service | B13: Proprietário, sócio-operador, Diretor de Marketing de rede de alimentação | C13: Cardápio impresso desatualizado, preços que mudam com o custo dos insumos e pouca visibilidade dos pratos de maior margem. | D13: Cada reimpressão de cardápio é custo; cada cliente que pede o prato de menor margem por falta de destaque é lucro perdido. | E13: Fazer o cardápio vender: mostrar o prato certo, na hora certa, com a cara de dar água na boca. | F13: Qual é o prato com a melhor margem da sua casa? E ele é o que mais aparece para o cliente? | G13: Happy hour: às 17h o menu board muda sozinho para chopp e petiscos; no almoço, o executivo; à noite, o prato assinatura em vídeo. O cardápio trabalha por turno. | H13: Destaque dos itens de maior margem, combos e upsell; transmissão de jogos e eventos que enchem a casa. | I13: Ambiente moderno e instagramável; fachada que chama de longe. | J13: Preço atualizado em minutos, sem reimpressão; programação automática por horário. | K13: Prato que não é visto não é pedido. | L13: Vamos colocar o seu cardápio para vender sozinho? | M13: Menu boards em LED, painel de fachada, telão para jogos e eventos, painéis decorativos. | N13: Participação na Abrasel. Inserir case de restaurante/rede. | O13: Quantas vezes por ano vocês reimprimem o cardápio? Transmitem jogos? Qual a diferença de margem entre o prato mais pedido e o mais lucrativo? | P13: Meu restaurante é pequeno para isso. | Q13: O painel é dimensionado para o seu espaço. Começamos pelo menu board ou pela fachada, onde o retorno é mais rápido. | R13: Ticket médio, vendas dos itens destacados, economia com impressão, ocupação em dias de evento. | S13: Simulação do menu board com o cardápio real do cliente. | T13: Entretenimento; Experiência; Eficiência operacional | V13: Preço; Fobia digital; Momento financeiro | W13: =COUNTIF('Banco de Ideias'!$C:$C,A13) -> 0
A14: Igrejas e Centros Religiosos | B14: Pastor/Padre responsável, Conselho/Diretoria, Ministério de Mídia e Louvor | C14: A mensagem precisa alcançar todos, do primeiro ao último banco e também quem assiste online. Projetores perdem brilho, letra de louvor não se lê, e a transmissão fica pobre. | D14: Quem não enxerga e não escuta se desconecta. A nova geração está acostumada com telas de alta qualidade e compara. | E14: Levar a mensagem com clareza a cada pessoa, presente ou online, e criar um ambiente de acolhimento e celebração. | F14: Quem está no último banco da sua igreja vê o culto com a mesma clareza de quem está na primeira fila? | G14: O mesmo culto com projetor (imagem lavada, luz acesa atrapalhando) e com painel de LED (letra nítida, imagem do pregador ampliada, transmissão bonita). A mensagem é a mesma; o alcance muda. | H14: Mais engajamento e permanência dos membros, eventos e conferências que atraem visitantes, transmissão de melhor qualidade que amplia o alcance. | I14: Louvor com letras legíveis, imagem ampliada do pregador, cenografia para datas especiais (Páscoa, Natal, conferências). | J14: Não depende de escurecer o templo, sem troca de lâmpadas de projetor, vida útil longa, suporte técnico. | K14: A mensagem merece ser vista por todos, do altar ao último banco. | L14: Vamos levar a sua mensagem com a clareza que ela merece? | M14: Painel de LED de palco (indoor, pixel pitch conforme distância), painéis laterais, telão para eventos (locação), fachada para comunicação com a comunidade. | N14: Expo Cristã SP; artigo 'Painel de LED para Igrejas'. Inserir case de igreja. | O14: Qual a distância do palco até o último banco? Vocês transmitem online? Quantos eventos especiais por ano? Como decidem investimentos (conselho, campanha)? | P14: Precisamos aprovar com a comunidade / fazer campanha de arrecadação. | Q14: Preparamos material para a apresentação ao conselho e à comunidade, com simulação do templo, e opções de parcelamento compatíveis com campanhas. | R14: Legibilidade/visibilidade em todos os assentos, audiência online, participação em eventos. | S14: Visita técnica ao templo para medir distâncias e simular o painel ideal. | T14: Insumo de trabalho; Experiência; Entretenimento | V14: Forma de pagamento; Insegurança técnica; Aprovação por financeiro | W14: =COUNTIF('Banco de Ideias'!$C:$C,A14) -> 0
A15: Hotéis, Parques, Clubes e Piscinas | B15: Gerente Geral, Diretor Comercial/Eventos, Presidente de clube, Diretor de Lazer | C15: Disputa por eventos corporativos e sociais, áreas de lazer sem experiência diferenciada e comunicação com hóspedes/associados dispersa. | D15: O evento corporativo vai para o concorrente que tem estrutura pronta; o associado/hóspede não percebe o valor do que paga. | E15: Transformar espaços em experiências: eventos mais fortes, lazer memorável e comunicação que encanta. | F15: Quando uma empresa escolhe onde fazer a convenção anual, o que faz ela escolher o seu espaço e não o do concorrente? | G15: Piscina com painel à noite: cinema ao ar livre, jogo da Seleção, festa temática. O mesmo espaço vira três produtos diferentes na mesma semana. | H15: Locação de salões com estrutura de LED inclusa (valor agregado ao pacote), eventos temáticos que geram receita extra, patrocínio. | I15: Experiências únicas na área de lazer, wayfinding e boas-vindas personalizadas. | J15: Estrutura fixa elimina locação a cada evento; painéis outdoor resistentes para áreas abertas. | K15: Espaço sem experiência é só metro quadrado. | L15: Vamos transformar o seu espaço no lugar que todo mundo quer reservar? | M15: Painéis fixos para salões de eventos, LED outdoor para piscinas e áreas abertas, totens de comunicação, telões para jogos. | N15: Campanha Google Ads 'Parques, Clubes e Hotéis' (segmento com alta qualificação). Artigo 'Painel de LED para Piscinas'. Inserir case. | O15: Quantos eventos por mês? Quanto vocês gastam ou repassam em locação de telão? Que experiências oferecem hoje na área de lazer? | P15: Já alugamos telão quando há evento. | Q15: Somando as locações de um ano, o painel próprio costuma se pagar rápido, e ainda vira diferencial de venda do seu espaço. Vamos fazer essa conta com os seus números? | R15: Taxa de ocupação de salões, receita por evento, satisfação de hóspedes/associados, economia com locação. | S15: Levantamento de eventos dos últimos 12 meses para cálculo de compra x locação. | T15: Entretenimento; Experiência; Status | U15: Beto Carrero World; Rosewood; Animalia | V15: Consumo de energia; Manutenção; Momento financeiro | W15: =COUNTIF('Banco de Ideias'!$C:$C,A15) -> 0
A16: Eventos, Agências e Produtoras | B16: Sócio da produtora/agência, Diretor de Produção, Diretor de Criação | C16: Prazo curto, cliente exigente e fornecedor que falha na montagem. Um painel com falha ao vivo queima a reputação da agência. | D16: Um evento que dá errado custa o cliente inteiro, não só aquele job. | E16: Ser o parceiro que garante que a ideia da agência apareça ao vivo exatamente como foi criada. | F16: Qual foi o pior momento técnico que você já viveu ao vivo num evento? Nosso trabalho é que ele nunca se repita. | G16: Circuito LedWave da Copa: ativações que movimentaram o mercado e elevaram a demanda por painéis de LED em 50%. Escala, prazo e operação ao vivo são o nosso dia a dia. | H16: Estoque, logística e equipe técnica próprios permitem atender jobs grandes e simultâneos, com margem previsível para a agência. | I16: Formatos criativos (curvos, 3D, piso, transparente) que fazem a ativação ser lembrada. | J16: Montagem, operação e backup técnico com equipe LedWave; presença em várias praças (Goiânia, SP, Brasília, EUA). | K16: Ao vivo não tem segunda chance. Tem LedWave. | L16: Qual é o próximo grande job? Vamos montar juntos? | M16: Locação de painéis indoor/outdoor, formatos especiais, operação técnica e conteúdo. | N16: Circuito LedWave da Copa (+50% demanda, imprensa). Eventos SA+ (fóruns regionais), NRF 2026. | O16: Quantos eventos por mês? Quais formatos o cliente mais pede? Quem é seu fornecedor hoje e o que falta nele? | P16: Tenho fornecedor mais barato. | Q16: Mais barato até o momento em que a tela apaga ao vivo. Compare estoque, equipe técnica, backup e histórico de entregas. Segurança também tem preço, e ela é mais barata que perder um cliente. | R16: Uptime ao vivo, prazo de montagem cumprido, recompra de clientes da agência. | S16: Cadastro como parceiro preferencial + tabela de locação para o próximo trimestre. | T16: Insumo de trabalho; Entretenimento; Experiência | V16: Preço; SLA; Concorrência | W16: =COUNTIF('Banco de Ideias'!$C:$C,A16) -> 0
A17: Corporativo (Comunicação Interna e Recepções) | B17: Diretor de RH/Comunicação Interna, Facilities, CEO, Marketing institucional | C17: Comunicação interna que ninguém lê (e-mail, mural, intranet). Recepção e auditório que não refletem o tamanho e a inovação da empresa. | D17: Colaborador desinformado é colaborador desengajado; visitante que entra numa recepção comum não sente a grandeza da empresa. | E17: Fazer a cultura da empresa ser vista e vivida todos os dias, por quem trabalha e por quem visita. | F17: Se um investidor entrasse hoje na sua recepção, em quantos segundos ele entenderia quem vocês são? | G17: Fábrica com 2.000 colaboradores: metas de segurança, aniversariantes e resultados no painel do refeitório. A informação chega a quem não tem e-mail corporativo. | H17: Engajamento e produtividade, redução de acidentes com comunicação de segurança, impacto em visitantes e clientes. | I17: Recepção e auditório com padrão de empresa global; eventos internos e convenções com estrutura própria. | J17: Gestão centralizada de mensagens para várias unidades; substitui murais e impressos. | K17: Cultura que não se vê não se vive. | L17: Vamos fazer a sua empresa contar a própria história todos os dias? | M17: Painel de recepção, auditório e sala de convenção, painéis em refeitórios/fábricas, videowall de comando. | N17: Artigo LedWave 'A comunicação interna como pilar estratégico'. Inserir case corporativo. | O17: Como a comunicação chega hoje a quem não tem e-mail? Quantas unidades? Quantos eventos internos por ano? | P17: Não é prioridade no orçamento deste ano. | Q17: Podemos começar pelo ponto de maior impacto (recepção ou fábrica) e planejar as próximas fases para o orçamento seguinte. | R17: Alcance da comunicação interna, engajamento em pesquisas de clima, indicadores de segurança. | S17: Diagnóstico de pontos de comunicação da empresa + proposta em fases. | T17: Branding; Status; Retrofit / arquitetura | V17: Aprovação por financeiro; Gestão de conteúdo; Percepção de valor | W17: =COUNTIF('Banco de Ideias'!$C:$C,A17) -> 0
A18: Educação (Escolas, Faculdades e Universidades) | B18: Mantenedor, Diretor Geral, Diretor de Marketing/Captação, Coordenador de TI | C18: Concorrência forte na captação de alunos, pais que comparam infraestrutura e comunicação com alunos que não chega. | D18: A família escolhe a escola em uma visita. Infraestrutura que parece antiga perde matrícula. | E18: Mostrar na prática que a instituição prepara para o futuro e informa a comunidade escolar com eficiência. | F18: Na visita de um pai à sua escola, o que mostra a ele que o filho vai estudar no futuro e não no passado? | G18: Auditório com painel de LED: formatura, feira de ciências, palestra e transmissão para a família que mora em outra cidade. Um investimento, dezenas de momentos que a família não esquece. | H18: Captação e retenção de alunos, eventos e formaturas com estrutura própria, locação do auditório para terceiros. | I18: Ambiente moderno, ensino com conteúdo visual de impacto, eventos memoráveis. | J18: Comunicação de avisos, horários e campanhas em todo o campus; substitui murais. | K18: Escola que mostra o futuro forma para o futuro. | L18: Vamos fazer a próxima visita de pais terminar em matrícula? | M18: Painel de auditório, LED de fachada e pátio, totens informativos, painéis para ginásio. | N18: Inserir case educacional. | O18: Quantas visitas de captação por ano e qual a conversão? Vocês têm auditório? Quantos eventos por ano? | P18: Orçamento de escola é apertado. | Q18: Por isso olhamos para o retorno: uma matrícula a mais por turma já paga parte do investimento, e o auditório pode gerar receita com locação. | R18: Conversão de visitas em matrícula, uso do auditório, alcance de comunicados. | S18: Visita técnica ao auditório/pátio + simulação de payback por matrícula. | T18: Insumo de trabalho; Experiência; Status | U18: Museu do Amanhã | V18: Momento financeiro; Forma de pagamento; Fobia digital | W18: =COUNTIF('Banco de Ideias'!$C:$C,A18) -> 0
A19: Saúde (Hospitais, Clínicas e Laboratórios) | B19: Diretor Administrativo, Diretor de Marketing, Gerente de Hotelaria Hospitalar | C19: Sala de espera ansiosa, informação desencontrada e marca que precisa transmitir confiança e tecnologia. | D19: Paciente ansioso tem percepção pior do atendimento; percepção ruim vira avaliação negativa e perda de convênio/particular. | E19: Acolher o paciente com informação clara, reduzir a ansiedade da espera e mostrar a tecnologia que existe por trás do cuidado. | F19: Quanto tempo o seu paciente espera, e o que ele sente nesse tempo? | G19: Recepção de laboratório: chamada por senha clara, tempo estimado, conteúdo de prevenção e a apresentação dos novos exames. A mesma espera, outra experiência. | H19: Divulgação de serviços e check-ups (cross-sell), patrocínio de indústria farmacêutica/saúde quando permitido. | I19: Ambiente acolhedor e moderno, comunicação de prevenção, sinalização clara. | J19: Chamada de pacientes e wayfinding integrados, atualização remota em todas as unidades. | K19: Tecnologia que cuida começa na recepção. | L19: Vamos transformar a espera do seu paciente em cuidado? | M19: Painéis de recepção e chamada, totens de wayfinding, fachada, painéis em auditório para congressos. | N19: Inserir case de saúde. | O19: Qual o tempo médio de espera? Quantas unidades? Como os pacientes avaliam a recepção hoje? | P19: Ambiente de saúde tem restrições técnicas e normativas. | Q19: Dimensionamos brilho, instalação e conteúdo para o ambiente, seguindo as normas e as orientações da equipe de engenharia clínica. | R19: NPS da recepção, percepção de tempo de espera, vendas de check-ups divulgados. | S19: Diagnóstico de jornada do paciente na unidade principal. | T19: Eficiência operacional; Experiência; Branding | V19: Insegurança técnica; Aprovação por financeiro; Consumo de energia | W19: =COUNTIF('Banco de Ideias'!$C:$C,A19) -> 0
A20: Arenas, Estádios, Academias e Esportes | B20: Presidente/Diretor de clube, Gestor de arena, Dono de rede de academias, Marketing esportivo | C20: Patrocinador quer exposição medida, torcedor quer espetáculo e academia precisa reter aluno num mercado de preço. | D20: Placa estática vende uma marca por vez; painel digital vende várias. Quem não digitaliza deixa receita de patrocínio na mesa. | E20: Transformar cada jogo, aula e treino em espetáculo e cada metro de placa em receita de patrocínio. | F20: Quantos patrocinadores cabem em uma placa estática? E em um painel de LED? | G20: Placa de campo digital: no mesmo jogo, 20 patrocinadores em rotação, replay, gol em animação e a torcida filmando. O espaço é o mesmo; a receita multiplica. | H20: Mais cotas de patrocínio no mesmo espaço, ativações e naming de momentos (gol, intervalo). | I20: Espetáculo para torcedor e aluno; aulas coletivas imersivas; telão em arena. | J20: Gestão de inserções e comprovação para patrocinadores; painéis resistentes para uso intenso. | K20: Placa estática vende uma marca. LED vende o jogo inteiro. | L20: Vamos multiplicar a receita do seu espaço sem aumentar um metro? | M20: Placas de campo (perimetrais), telões de arena, painéis para academias e salas de aulas coletivas. | N20: Circuito LedWave da Copa. Inserir case esportivo. | O20: Quantos patrocinadores vocês têm e quantos querem ter? Quantos jogos/eventos por ano? Como comprovam exposição? | P20: O investimento inicial é alto para o clube. | Q20: Desenhamos o projeto com os patrocinadores: as novas cotas digitais ajudam a pagar o painel. Podemos estruturar a conta com o seu comercial. | R20: Número de cotas vendidas, receita de patrocínio, retenção de alunos, público. | S20: Simulação de inventário de patrocínio digital com os números do clube/arena. | T20: Entretenimento; Mídia; Experiência | V20: Crédito; Manutenção; Fabricação de estrutura metálica | W20: =COUNTIF('Banco de Ideias'!$C:$C,A20) -> 0
A21: Poder Público e Mobiliário Urbano | B21: Secretário (Comunicação, Turismo, Mobilidade), Prefeito, Concessionárias de mobiliário urbano | C21: Comunicar com o cidadão de forma rápida (alertas, serviços, eventos) e modernizar a cidade com orçamento limitado. | D21: Comunicação lenta em emergências e cidade que não se valoriza turisticamente. | E21: Uma cidade que informa, acolhe e se orgulha: tecnologia a serviço do cidadão. | F21: Em uma emergência na sua cidade, quanto tempo leva para o cidadão na rua receber a informação? | G21: Brasília ganhou um ícone: o Boulevard.Live, o maior painel de LED da América Latina. Um painel bem posicionado vira ponto turístico, canal de utilidade pública e mídia. | H21: Modelos de concessão/PPP em que a mídia comercial custeia o equipamento e o espaço público. | I21: Valorização turística, eventos públicos, orgulho da cidade. | J21: Comunicação de utilidade pública em tempo real (trânsito, defesa civil, saúde). | K21: Cidade que informa é cidade que cuida. | L21: Vamos desenhar juntos o modelo que moderniza a cidade sem pesar no orçamento? | M21: Mobiliário urbano digital, painéis de utilidade pública, telões para eventos públicos, painéis de turismo. | N21: Boulevard.Live (1.125 m²); artigo 'Inovação no mobiliário urbano com painéis de LED'; equipe de licitações. | O21: Quais canais vocês usam para alertas hoje? Existem concessões de mobiliário urbano em andamento? Há eventos públicos recorrentes? | P21: Precisa passar por licitação. | Q21: Temos equipe dedicada a licitações e apoiamos na especificação técnica correta, para que a cidade compre qualidade e não apenas o menor preço. | R21: Alcance da comunicação pública, receita de concessão, eventos realizados. | S21: Reunião técnica para apoiar termo de referência ou estudo de concessão. | T21: Mídia; Experiência; Retrofit / arquitetura | U21: Museu do Amanhã | V21: Política local / licenças; Consumo de energia; SLA | W21: =COUNTIF('Banco de Ideias'!$C:$C,A21) -> 0

Sheet SPIN por Nicho
A1: SPIN Selling por Nicho: perguntas inteligentes
A2: Situação → Problema → Implicação → Necessidade de solução. Faça poucas de Situação (pesquise antes) e mais de Implicação.
A3: Nicho | B3: S · Situação (contexto, pesquise antes) | C3: P · Problema (onde dói) | D3: I · Implicação (quanto custa a dor) | E3: N · Necessidade (o cliente diz o valor) | F3: Pergunta nova do gestor
A4: Varejo de Moda e Vitrines | B4: Quantas lojas vocês têm e quantas trocas de coleção/campanha fazem por ano? Como a vitrine é produzida hoje? | C4: O que mais atrasa ou encarece uma troca de vitrine? Já perderam uma promoção por não dar tempo de imprimir? | D4: Se a vitrine fica a mesma por semanas, o que acontece com o fluxo de quem passa todo dia na frente? Quanto isso pesa na venda da coleção nova? | E4: Se você pudesse trocar a vitrine de todas as lojas pelo celular, em minutos, o que faria diferente na próxima campanha?
A5: Supermercados, Atacarejos e Home Centers | B5: Quantas lojas e checkouts? Como as ofertas são comunicadas hoje? A indústria investe em trade nas suas lojas? | C5: Quanto tempo leva para uma oferta sair do comercial e chegar à gôndola? O fornecedor pede comprovação de exposição? | D5: Quanto de verba de trade vira papel que ninguém mede? Quanto você deixa de faturar por não vender mídia dentro da loja? | E5: Se as telas fossem pagas pela indústria e ainda gerassem receita, quantas lojas você colocaria no piloto?
A6: Farmácias e Drogarias | B6: Quantas lojas, e quantas abrem por ano? Como funciona a parceria com a indústria hoje? | C6: Como vocês se diferenciam das farmácias concorrentes na mesma rua? Campanhas sazonais chegam a tempo em todas as lojas? | D6: Se o cliente escolhe a farmácia mais visível, quanto fluxo vocês perdem por ter fachada igual às outras? E quanto a indústria investiria se tivesse onde? | E6: Uma rede de telas que se paga com a indústria e destaca a sua fachada ajudaria na meta deste ano?
A7: Postos de Combustível e Conveniência | B7: Quantos postos, qual o fluxo diário da via, qual o peso da conveniência no resultado? | C7: Como o preço é atualizado hoje? A conveniência é vista da pista? Algum anunciante local já procurou vocês? | D7: Quantos motoristas passam reto por não verem o preço ou a oferta a tempo? Quanto vale um ponto a mais de conversão da pista? | E7: Se o mesmo totem mostrasse preço, promoção da conveniência e ainda vendesse mídia, como isso mudaria a margem do posto?
A8: DOOH e Investidores de Mídia | B8: Quantos pontos opera, em quais praças, com que ocupação média? Quem é seu fornecedor atual? | C8: Quanto tempo de tela apagada teve no último ano? Qual a maior dificuldade: ponto, licenciamento, venda ou manutenção? | D8: Quanto custou em receita cada dia de tela apagada? Quantos pontos bons a concorrência ocupou enquanto você decidia? | E8: Um parceiro que fabrica, mantém e entende de operação de mídia aceleraria o seu plano de expansão?
A9: Shopping Centers | B9: Qual o fluxo mensal, quais as datas mais fortes e como está a receita de mall media? | C9: O mall media atual é fácil de vender? O shopping tem um ponto de experiência que gera visita espontânea? | D9: Se o shopping não é destino, quanto da visita migra para o online ou para o concorrente? Quanto inventário de mídia fica sem venda? | E9: Uma experiência-âncora que gera fluxo e mídia premium ajudaria no próximo Natal?
A10: Concessionárias de Veículos | B10: Quantas lojas e marcas? Quantos lançamentos por ano? Como é o showroom hoje? | C10: O cliente chega já decidido pela internet? O que o showroom oferece que o site não oferece? | D10: Quantas vendas se perdem quando o cliente sai do showroom sem emoção? Quanto custa cada evento de lançamento sem estrutura própria? | E10: Se o showroom pudesse colocar o cliente na estrada antes do test-drive, como isso afetaria a conversão?
A11: Construtoras e Stands de Vendas | B11: Quantos lançamentos e qual o VGV do próximo? Quanto tempo dura um stand? | C11: O visitante entende o empreendimento só com maquete e perspectivas? Qual a conversão de visita em proposta? | D11: Cada mês a mais de ciclo de vendas custa quanto em custo financeiro da obra? Quantas visitas saem sem se imaginar no imóvel? | E11: Se o stand fizesse o cliente viver o apartamento e o painel fosse reaproveitado nos próximos lançamentos, faria sentido avaliar?
A12: Franquias e Redes | B12: Quantas unidades, quantas aberturas previstas, qual o kit de abertura hoje? | C12: Quanto tempo leva para uma campanha nacional chegar a todas as lojas? Os franqueados aplicam o material corretamente? | D12: Qual o custo de uma campanha impressa multiplicado pelo número de lojas? O que a inconsistência faz com o valor da marca? | E12: Se uma campanha chegasse a todas as lojas em um clique, padronizada, quanto isso valeria para a rede e para o franqueado?
A13: Bares, Restaurantes e Food Service | B13: Quantas casas, quais turnos, transmitem jogos/eventos? Como é o cardápio hoje? | C13: Quantas vezes por ano reimprimem o cardápio? Os pratos de maior margem estão em destaque? | D13: Quanto deixam de ganhar quando o cliente pede o item de menor margem por falta de destaque? Quanto custam as reimpressões? | E13: Se o cardápio mudasse sozinho por turno e destacasse o que dá mais lucro, quanto isso mudaria no ticket médio?
A14: Igrejas e Centros Religiosos | B14: Qual a capacidade do templo e a distância do palco ao último banco? Vocês transmitem online? Usam projetor? | C14: Quem está no fundo consegue ler as letras e ver o pregador? A transmissão tem a qualidade que vocês gostariam? | D14: Quando as pessoas não enxergam bem, o que acontece com a participação no louvor e na mensagem? E com a audiência online? | E14: Se toda a comunidade, presente e online, visse a mensagem com clareza, como isso fortaleceria o ministério?
A15: Hotéis, Parques, Clubes e Piscinas | B15: Quantos eventos por mês, quais espaços, quanto gastam ou repassam em locação de telão? | C15: Já perderam eventos para concorrentes com melhor estrutura? A área de lazer tem programação noturna? | D15: Quanto somam as locações no ano? Quanto vale um evento corporativo perdido? | E15: Uma estrutura fixa que vira diferencial de venda e gera novos produtos de lazer faria sentido no plano do ano?
... A21: Poder Público e Mobiliário Urbano | B21: Quais canais de comunicação com o cidadão existem? Há concessões ou projetos de cidade inteligente? | C21: A informação de emergência chega rápido a quem está na rua? A cidade tem pontos turísticos digitais? | D21: Quanto custa uma comunicação lenta em emergências? Quanto a cidade perde em turismo e eventos? | E21: Um modelo em que a mídia custeia o equipamento e a cidade ganha comunicação pública faria sentido?

Sheet Orçamento por Nicho
A1: Orçar certo por nicho: o que levantar antes da proposta
A2: Proposta boa nasce de briefing bom. Use na visita técnica e na reunião de descoberta.
A3: Nicho | B3: Dados técnicos essenciais | C3: Qualificação (decisor, orçamento, prazo) | D3: Armadilhas de orçamento | E3: Observações do gestor
A4: Varejo de Moda e Vitrines | B4: Medidas da vitrine; vidro (painel atrás do vidro = alto brilho ou LED transparente); incidência de sol; horário de funcionamento; distância da calçada; nº de lojas. | C4: Quem aprova (marketing ou dono)? Orçamento por loja ou para a rede? Data da próxima coleção? | D4: Orçar brilho de indoor para vitrine com sol direto; esquecer o calendário de coleções como prazo.
A5: Supermercados, Atacarejos e Home Centers | B5: Nº de lojas e checkouts; pontos (entrada, gôndola, checkout, fachada); infraestrutura de rede/energia; integração com preços. | C5: Trade/marketing ou operações decide? Indústria vai cofinanciar? Piloto em quantas lojas? | D5: Orçar só hardware sem modelo de retail media e gestão de conteúdo.
A6: Farmácias e Drogarias | B6: Fachada (medidas, manual da marca); áreas internas; nº de lojas e aberturas; regras do franqueador. | C6: Franqueador aprova? Indústria cofinancia? Meta de rollout? | D6: Ignorar manual de marca e aprovação do franqueador.
A7: Postos de Combustível e Conveniência | B7: Totem existente (medidas, estrutura); distância e velocidade da via; exposição a sol/chuva (IP65); bandeira e regras da distribuidora. | C7: Proprietário decide sozinho? Bandeira exige padrão? Prazo da reforma? | D7: Pixel pitch fino demais (caro e desnecessário para leitura a distância); esquecer aprovação da bandeira.
A8: DOOH e Investidores de Mídia | B8: Ponto (endereço, fluxo, ângulo, distância); estrutura e laudo; licenciamento municipal; energia; horas de operação/dia. | C8: Capital próprio ou financiado? Expectativa de payback? Já tem anunciantes? | D8: Orçar o painel sem validar licença e estrutura; subestimar manutenção e uptime.
A9: Shopping Centers | B9: Local (praça, empena, fachada); medidas; formato (curvo, 3D anamórfico); distância do público; integração com mall media. | C9: Superintendência ou administradora aprova? Orçamento CAPEX do ano? Data-alvo (Natal)? | D9: Perder a janela de aprovação do orçamento anual do shopping.
A10: Concessionárias de Veículos | B10: Parede do showroom (medidas); distância de visualização; fachada; necessidade de painel móvel para eventos. | C10: Grupo ou loja decide? Montadora cofinancia? Próximo lançamento? | D10: Não envolver a regional da montadora.
A11: Construtoras e Stands de Vendas | B11: Medidas do stand e do tapume; tempo de permanência; reaproveitamento previsto; outdoor x indoor. | C11: Incorporação ou marketing decide? Compra ou locação? Data do lançamento? | D11: Orçar compra quando o caso é locação (ou vice-versa) sem mostrar o comparativo.
A12: Franquias e Redes | B12: Formatos de loja; nº de unidades e aberturas; padrão visual; quem paga (franqueador/franqueado). | C12: Diretor de expansão aprova kit? Fornecedor homologado? Financiamento ao franqueado? | D12: Orçar loja a loja em vez de um kit padrão homologado.
A13: Bares, Restaurantes e Food Service | B13: Pontos (menu board, fachada, salão); medidas; distância do balcão; horas de operação. | C13: Dono decide? Orçamento por casa? Abertura/reforma prevista? | D13: Superdimensionar; menu board precisa de leitura de perto (pitch mais fino).
A14: Igrejas e Centros Religiosos | B14: Largura e altura do palco; distância ao primeiro e ao último banco; iluminação; transmissão; estrutura (piso ou suspenso). | C14: Pastor, conselho ou assembleia aprova? Campanha de arrecadação? Data (Páscoa, Natal, conferência)? | D14: Ignorar a distância do primeiro banco (define o pitch); não preparar material para o conselho.
A15: Hotéis, Parques, Clubes e Piscinas | B15: Espaços (salões, piscina, área aberta); outdoor (IP65); medidas; histórico de locações. | C15: Gerente geral ou conselho? CAPEX ou OPEX? Alta temporada? | D15: Orçar indoor para área aberta/molhada.
... A21: Poder Público e Mobiliário Urbano | B21: Locais; especificação técnica; normas; modelo (compra, concessão, PPP). | C21: Há dotação orçamentária? Modalidade de licitação? Prazo do edital? | D21: Especificação técnica genérica que abre espaço para menor preço sem qualidade.
A23: Referência técnica rápida
A24: Tema | B24: Regra prática | C24: Fonte / validação
A25: Pixel pitch x distância | B25: Regra prática: distância mínima de visualização (m) ≈ pixel pitch (mm). Distância confortável ≈ 2 a 3 vezes isso. Ex.: P3,9 → a partir de ~4 m, ideal 8 a 12 m. | C25: Referência de mercado; validar com a engenharia LedWave.
A26: Brilho indoor x outdoor | B26: Indoor: tipicamente 800 a 1.500 nits. Outdoor/vitrine com sol: 4.500 nits ou mais. | C26: Referência de mercado; validar com a ficha técnica.
A27: Proteção | B27: Outdoor e áreas molhadas exigem grau de proteção IP65 ou superior na frente. | C27: Referência de mercado.
A28: Compra x locação | B28: Uso recorrente (≥ alguns eventos por mês ou uso diário) tende a favorecer compra; uso pontual favorece locação. Sempre mostrar o comparativo. | C28: Montar com os números do cliente.
A29: Custo total | B29: Orçamento completo = painel + estrutura + processador/player + instalação + conteúdo/gestão + garantia/manutenção (+ frete, montagem e técnico em locação). | C29: Planilha MC_EVENTOS (Drive) como base de locação.
A31: Checklist universal da proposta
A32: ☐ | B32: Dor do cliente nas palavras dele (da descoberta)
A33: ☐ | B33: Decisor e critério de decisão mapeados
A34: ☐ | B34: Medidas, distância de visualização e ambiente (indoor/outdoor)
A35: ☐ | B35: Compra x locação comparadas
A36: ☐ | B36: Custo total (painel, estrutura, instalação, conteúdo, manutenção)
A37: ☐ | B37: KPIs que o cliente vai medir
A38: ☐ | B38: Prova social do mesmo nicho
A39: ☐ | B39: Próximo passo com data

Sheet Objeções
A1: Objeções e respostas
A2: Método: Ouvir → Acolher → Explorar → Responder com prova → Confirmar (detalhes na aba Escuta Ativa). Adicione as respostas que funcionaram em campo.
A3: Nicho | B3: Objeção | C3: Resposta | D3: Técnica | E3: Funcionou em campo? (gestor) | F3: Variação testada
A4: Todos (insight do comercial) | B4: Fobia digital | C4: Atualizar a tela é tão simples quanto postar no Instagram. Treinamos a sua equipe, e a LedWave pode cuidar do conteúdo para você. | D4: Percepção · Leve: Demonstração do software no celular
A5: Todos (insight do comercial) | B5: Preço | C5: Vamos comparar o custo total: impressos, locações e vendas perdidas de um ano contra o investimento no painel, que fica com você por muitos anos. | D5: Financeira · Leve: Planilha de custo total / payback
A6: Todos (insight do comercial) | B6: Qualidade | C6: Venha ver de perto: fabricamos no Brasil, com garantia e suporte próprio. E marcas como Rosewood e Museu do Amanhã aprovaram essa qualidade. | D6: Técnica · Leve: Visita ao showroom + cases
A7: Todos (insight do comercial) | B7: Gestão de conteúdo | C7: Você não fica sozinho: entregamos o software, o treinamento e, se quiser, a produção e a programação do conteúdo. | D7: Operacional · Leve: Pacote de conteúdo
A8: Todos (insight do comercial) | B8: Fabricação de estrutura metálica | C8: A estrutura faz parte do projeto: dimensionamos, fabricamos e instalamos com responsabilidade técnica, sem você precisar de outro fornecedor. | D8: Técnica · Leve: Projeto estrutural + ART
A9: Todos (insight do comercial) | B9: Manutenção | C9: Temos equipe técnica e estoque de peças próprios, e oferecemos contrato de manutenção preventiva. | D9: Operacional · Leve: Contrato de manutenção
A10: Todos (insight do comercial) | B10: SLA | C10: O prazo de atendimento fica escrito no contrato. [Preencher prazos oficiais de SLA] | D10: Operacional · Leve: Contrato com SLA
A11: Todos (insight do comercial) | B11: Política comercial | C11: Explique as condições com transparência e leve a proposta já dentro da alçada aprovada, com alternativas. | D11: Financeira · Leve: Tabela de condições
A12: Todos (insight do comercial) | B12: Política local / licenças | C12: Apoiamos o licenciamento: projeto técnico, documentação e orientação sobre as regras da sua cidade. | D12: Regulatória · Leve: Checklist de licenciamento
A13: Todos (insight do comercial) | B13: Forma de pagamento | C13: Temos opções: à vista, parcelado, financiamento e locação. Montamos a que cabe no seu fluxo de caixa. | D13: Financeira · Leve: Simulação de pagamento
A14: Todos (insight do comercial) | B14: Política de pagamento / locação / WDC | C14: [Confirmar o que é WDC] Apresente as regras de pagamento e locação de forma simples, com um exemplo numérico. | D14: Financeira · Leve: Tabela de condições
A15: Todos (insight do comercial) | B15: Momento financeiro | C15: Podemos começar por um piloto ou pela locação, que vira despesa mensal em vez de investimento, e crescer por fases. | D15: Financeira · Leve: Proposta em fases
... A48: Poder Público e Mobiliário Urbano | B48: Precisa passar por licitação. | C48: Temos equipe dedicada a licitações e apoiamos na especificação técnica correta, para que a cidade compre qualidade e não apenas o menor preço. | D48: Específica do nicho

Sheet Frases de Efeito
A1: Banco de frases de efeito
A2: Frases curtas, ritmadas e repetíveis. Diga, pause 3 segundos, deixe o silêncio trabalhar.
A3: Momento / Nicho | B3: Frase | C3: Autor | D3: Nota do time (1 a 5)
A4: Institucional | B4: Não vendemos painel. Entregamos o resultado que o painel gera. | C4: Playbook v1
A5: Institucional | B5: Começamos com R$ 12 mil e uma ideia. Hoje iluminamos o Brasil. | C5: Playbook v1
A6: Institucional | B6: Fizemos o maior painel de LED da América Latina. O seu vai ter o mesmo padrão. | C6: Playbook v1
A7: Institucional | B7: Quatro anos seguidos entre as empresas que mais crescem no Brasil. Número 1 do nosso segmento. | C7: Playbook v1
A8: Institucional | B8: Fabricamos no Brasil, operamos nos EUA, buscamos tecnologia na China. | C8: Playbook v1
A9: Abertura | B9: Seu espaço já tem audiência. A pergunta é o que ela está vendo. | C9: Playbook v1
A10: Abertura | B10: Toda empresa comunica. Poucas encantam. | C10: Playbook v1
A11: Transição | B11: E é por isso que estamos aqui. | C11: Playbook v1
A12: Transição | B12: Agora imagine o seu espaço assim. | C12: Playbook v1
A13: Valor | B13: Tela apagada é resultado zero. | C13: Playbook v1
A14: Valor | B14: A tela deixa de ser custo e passa a gerar receita. | C14: Playbook v1
A15: Valor | B15: O olho humano segue movimento. Quem se move é visto. | C15: Playbook v1
... A53: Poder Público e Mobiliário Urbano (fechamento) | B53: Vamos desenhar juntos o modelo que moderniza a cidade sem pesar no orçamento? | C53: Playbook v1

Sheet Prospecção Outbound
A1: Prospecção outbound: cadência e script de ligação
A2: Objetivo do outbound é AGENDAR uma conversa de descoberta, não vender o painel. Personalize com o gatilho e a dor do nicho.
A3: Dia | B3: Canal | C3: Ação | D3: Objetivo | E3: Modelo de mensagem
A4: D0 | B4: Pesquisa | C4: Estudar a conta: site, Instagram, Google Maps/Street View da fachada, notícias, LinkedIn do decisor. Anotar 1 gatilho (inauguração, reforma, lançamento, expansão, evento). | D4: Ter um motivo real e específico para o contato. | E4: —
A5: D1 | B5: LinkedIn | C5: Pedido de conexão sem pitch, com nota personalizada. | D5: Ser reconhecido antes da ligação. | E5: {Nome}, acompanho a {Empresa} e vi {gatilho}. Trabalho com comunicação digital para {nicho}. Seria bom ter você na rede.
A6: D2 | B6: Ligação | C6: Cold call de 2 a 3 minutos. Objetivo: agendar 20 minutos, não vender. | D6: Agendar diagnóstico. | E6: Ver aba Script Cold Call.
A7: D2 | B7: WhatsApp | C7: Mensagem curta pós-ligação (atendeu ou não). | D7: Deixar registro e um gancho. | E7: {Nome}, aqui é {Vendedor}, da LedWave. Tentei falar com você sobre {gatilho}. Tenho uma ideia de como {dor do nicho em 1 linha}. Faz sentido 20 min na {dia}?
A8: D4 | B8: E-mail | C8: E-mail com insight do nicho (Challenger) + 1 imagem antes/depois. | D8: Ensinar algo novo. | E8: Assunto: {Empresa} + uma ideia para {dor}. Corpo: 1 insight + 1 prova + 1 pergunta. Máx. 90 palavras.
A9: D6 | B9: Ligação | C9: Segunda tentativa em outro horário (início da manhã ou fim da tarde). | D9: Agendar. | E9: Abrir citando o e-mail: 'Te mandei uma imagem de como ficaria a fachada de vocês...'
A10: D8 | B10: LinkedIn/Instagram | C10: Interagir com conteúdo do decisor ou da empresa; enviar case do mesmo nicho. | D10: Prova social. | E10: {Nome}, fizemos isso para uma {empresa do nicho}. Lembrei de vocês por causa de {gatilho}.
A11: D11 | B11: Vídeo/áudio | C11: Vídeo de 45 s (ou áudio) personalizado com mockup da fachada/espaço do cliente. | D11: Quebrar o padrão. | E11: Mostrar o espaço dele com o painel e fazer 1 pergunta.
A12: D14 | B12: E-mail de término | C12: E-mail 'break-up' educado. | D12: Gerar resposta. | E12: {Nome}, imagino que não seja prioridade agora. Posso encerrar por aqui ou volto a falar em {mês}? Uma palavra já me ajuda.
A14: Script de cold call (2 a 3 minutos)
A15: Etapa | C15: O que dizer | D15: Por que funciona
A16: 1. Permissão (10 s) | C16: Oi, {Nome}? Aqui é {Vendedor}, da LedWave. Eu te liguei sem avisar. Posso te tomar 30 segundos e você decide se continuamos? | D16: Reduz a defesa. Quem dá permissão escuta.
A17: 2. Motivo (20 s) | C17: Vi que {gatilho: vocês estão abrindo a loja X / lançando o empreendimento Y}. Nós trabalhamos com {nicho} e normalmente as empresas nos chamam quando {dor do nicho}. | D17: Mostra que você estudou. Fala da dor, não do produto.
A18: 3. Pergunta de dor (30 s) | C18: Isso acontece por aí também, ou vocês já resolveram? (Escolha 1 pergunta de Problema da aba SPIN por Nicho) | D18: Pergunta aberta. Cale-se e escute.
A19: 4. Escuta + aprofundamento | C19: Entendi. Quando você diz '{palavra do cliente}', o que isso significa na prática? E quanto isso custa hoje? | D19: Espelhamento + implicação.
A20: 5. Mini-prova (15 s) | C20: Fizemos algo parecido para {empresa do nicho}, e {resultado/qualitativo}. Somos a LedWave, número 1 do segmento no ranking da Exame. | D20: Uma prova só, do mesmo nicho.
A21: 6. Pedido de reunião | C21: Faz sentido conversarmos 20 minutos para eu entender o seu cenário e te mostrar como ficaria no seu espaço? Terça às 10h ou quinta às 15h? | D21: Fechamento por escolha. Objetivo é a agenda, não a venda.
A22: Objeção: 'Me manda por e-mail' | C22: Mando sim. Para não te mandar algo genérico: qual é hoje o seu maior desafio com {dor}? Assim o material já vai certo, e eu te ligo na quinta para ver se fez sentido. | D22: Transformar a fuga em qualificação.
A23: Objeção: 'Não tenho interesse' | C23: Justo. Só por curiosidade: é porque já resolveram {dor} ou porque não é prioridade agora? | D23: Descobrir o motivo real.
A24: Objeção: 'Já tenho fornecedor' | C24: Ótimo, é sinal de que vocês valorizam isso. Se tivesse uma coisa que você melhoraria no seu fornecedor atual, qual seria? | D24: Encontrar a brecha.
A26: Gatilhos de prospecção por nicho (onde procurar o motivo do contato)
A27: • | C27: Inauguração ou reforma de loja (Instagram, Google Maps, imprensa local)
A28: • | C28: Lançamento imobiliário ou de veículo (sites de construtoras, montadoras)
A29: • | C29: Expansão de rede ou franquia (ABF, notícias, vagas abertas)
A30: • | C30: Participação em feiras do setor (APAS, Abrasel, ExpoPostos, Abrafarma, Expo Cristã)
A31: • | C31: Troca de liderança de marketing/trade (LinkedIn)
A32: • | C32: Edital, licitação ou concessão de mobiliário urbano (portais de compras)
A33: • | C33: Fachada antiga ou impressos desbotados (Street View)

Sheet Escuta Ativa
A1: Escuta ativa e tratamento de objeções
A2: Quem pergunta conduz. Quem escuta entende o que orçar e como fechar.
A3: Técnica | B3: Como aplicar | C3: Exemplo
A4: Regra 70/30 | B4: O cliente fala 70% do tempo na descoberta. Se você está falando mais, está vendendo cedo demais. | C4: Cronometre um roleplay: quem falou mais?
A5: Silêncio de 3 segundos | B5: Depois de uma resposta, conte até 3 antes de falar. O cliente costuma completar com a informação mais valiosa. | C5: —
A6: Espelhamento | B6: Repita as últimas 2 ou 3 palavras do cliente em tom de pergunta. Ele aprofunda sozinho. | C6: Cliente: '...a troca de campanha é um caos.' Você: 'Um caos?'
A7: Rotulagem (labeling) | B7: Nomeie a emoção ou a situação: 'Parece que…', 'Dá a impressão de que…'. | C7: 'Parece que a operação de impressos tira tempo do seu time.'
A8: Paráfrase + confirmação | B8: Resuma com as palavras dele e peça confirmação. Evita proposta errada. | C8: 'Se eu entendi bem, o principal é X, depois Y. Correto?'
A9: Anotar as palavras do cliente | B9: Use no fechamento exatamente as palavras que ele usou na descoberta. | C9: Ele disse 'caos'? Na proposta: 'fim do caos na troca de campanha'.
A10: Pergunta 'o que mais?' | B10: Antes de seguir, pergunte 'o que mais?'. A segunda dor costuma ser a mais importante. | C10: —
A11: Não interromper nem completar frases | B11: Interromper sinaliza que você já sabe a resposta, e o cliente para de contar. | C11: —
A12: Escutar o não dito | B12: Observe hesitação, mudança de tom, quem olha para quem numa reunião com mais de uma pessoa. | C12: 'Notei que você hesitou quando falamos de prazo. O que te preocupa?'
A14: Método para converter objeções em avanço
A15: Passo | B15: Como fazer
A16: 1. Ouvir até o fim | B16: Não interrompa. A objeção dita pela metade esconde a real.
A17: 2. Acolher | B17: 'Faz sentido você pensar nisso.' Nunca 'mas'; use 'e'.
A18: 3. Explorar (isolar) | B18: 'Além disso, tem mais alguma coisa que te impede de seguir?' e 'O que te faz pensar assim?'
A19: 4. Responder com prova | B19: Resposta da aba Objeções + 1 prova (case, número, garantia).
A20: 5. Confirmar | B20: 'Isso responde a sua dúvida?' Se sim, avance para o próximo passo na hora.
A21: Indicador | B21: Taxa de conversão de objeções = objeções superadas que avançaram de etapa ÷ objeções registradas. Registre no Banco de Ideias as respostas que funcionaram.

Sheet Roleplay
A1: Roleplay 1: Rede de farmácias
A2: Um faz o vendedor, outro faz a cliente, um terceiro avalia. Depois troquem os papéis e o nicho.
A4: Cenário
A5: Nicho | C5: Farmácias e Drogarias
A6: Cliente (persona) | C6: Marta, Diretora de Marketing de uma rede regional com 38 lojas, 4 aberturas previstas no ano. Pragmática, ocupada, já foi abordada por fornecedores de TV/digital signage.
A7: Contexto | C7: Primeira reunião por vídeo, 20 minutos, agendada após cold call. Gatilho: a rede anunciou novas lojas no Instagram.
A8: Objetivo do vendedor | C8: Descobrir dor, implicação e decisores, e sair com visita técnica agendada na loja âncora.
A9: Instruções para quem faz a Marta | C9: Responda de forma curta no início. Só abra informações se o vendedor fizer boas perguntas. Use 2 objeções: 'Já tentamos TVs e ninguém olhava' e 'Preciso ver com o diretor financeiro'. Revele, só se perguntarem, que a indústria pediu mais exposição nas lojas.
A10: Tempo | C10: 15 minutos de roleplay + 10 minutos de feedback.
A12: Script de referência (não é para decorar; é para entender a lógica)
A13: Etapa | B13: Quem fala | C13: Fala | D13: Técnica usada
A14: Abertura | B14: Vendedor | C14: Marta, obrigado pelo tempo. Para aproveitar bem os 20 minutos: queria entender o momento da rede, te mostrar uma ou duas ideias e, se fizer sentido, combinar um próximo passo. Pode ser? | D14: Agenda clara + permissão
A15: Abertura | B15: Cliente | C15: Pode. Mas já adianto que temos pouco tempo. | D15: —
A16: Situação | B16: Vendedor | C16: Vi que vocês vão abrir 4 lojas este ano. Parabéns. Como a comunicação nas lojas funciona hoje, das campanhas à fachada? | D16: Pergunta de Situação com gatilho
A17: Situação | B17: Cliente | C17: Basicamente impressos. A agência cria, a gráfica imprime e a gente distribui. | D17: —
A18: Problema | B18: Vendedor | C18: E quanto tempo leva entre a campanha ficar pronta e estar aplicada nas 38 lojas? | D18: Problema
A19: Problema | B19: Cliente | C19: Uns 10, 15 dias. Às vezes a campanha acaba e tem loja que ainda não aplicou. | D19: —
A20: Escuta ativa | B20: Vendedor | C20: Ainda não aplicou? | D20: Espelhamento (e silêncio)
A21: Escuta ativa | B21: Cliente | C21: É. E a indústria vive pedindo mais exposição, mas não temos espaço nem como provar o que foi exposto. | D21: Informação de ouro revelada
A22: Implicação | B22: Vendedor | C22: Deixa eu ver se entendi: a campanha chega atrasada em parte das lojas, e a indústria quer investir mas vocês não têm onde nem como provar. Quanto você acha que isso representa em verba de trade que vocês deixam de capturar por ano? | D22: Paráfrase + Implicação
A23: Implicação | B23: Cliente | C23: Nunca calculei. Mas não é pouco. | D23: —
A24: Objeção 1 | B24: Cliente | C24: Só que já testamos TV em duas lojas e ninguém olhava. | D24: Objeção
... A31: Fechamento | B31: Vendedor | C31: Fechado: quinta, 9h, na loja do centro. Te mando o convite agora e levo uma simulação da fachada com a identidade de vocês. Obrigado, Marta. | D31: Confirmação + próximo passo concreto
A33: Ficha de avaliação (nota de 1 a 5 nas células amarelas)
A34: Critério | C34: O que observar | D34: Comentário do avaliador | E34: Nota (1-5)
A35: Abertura com agenda e permissão | C35: Combinou objetivo e tempo da reunião?
A36: Uso do gatilho | C36: Citou algo específico da empresa do cliente?
A37: Perguntas SPIN | C37: Fez ao menos 1 pergunta de cada tipo (S, P, I, N)?
A38: Escuta ativa (70/30) | C38: O cliente falou mais que o vendedor? Usou espelhamento/silêncio?
A39: Paráfrase | C39: Resumiu a dor com as palavras do cliente?
A40: Tratamento de objeções | C40: Acolheu, explorou e respondeu com prova, sem discutir?
A41: Mapeamento de decisores | C41: Descobriu quem decide e quais critérios usa?
A42: Prova social do nicho | C42: Usou uma prova do mesmo nicho?
A43: Fechamento por escolha | C43: Saiu com próximo passo, data e hora?
A44: Tom e confiança | C44: Falou com calma, sem pressa e sem jargão técnico?
C45: Pontuação total (máx. 50) | E45: =SUM(E35:E44) -> 0
C46: Aproveitamento | E46: =IF(COUNT(E35:E44)=0,"-",SUM(E35:E44)/(5*COUNT(E35:E44))) -> -
C47: Leitura | E47: =IF(COUNT(E35:E44)=0,"-",IF(E46>=0.8,"Pronto para campo",IF(E46>=0.6,"Treinar 1 rodada","Repetir roleplay"))) -> -
A49: Próximos roleplays sugeridos
A50: Roleplay 2 | C50: Posto de combustível: proprietário que 'só olha preço' (cold call de 3 minutos)
A51: Roleplay 3 | C51: Igreja: pastor + tesoureiro, objeção de aprovação em conselho
A52: Roleplay 4 | C52: Supermercado: diretor de trade cético com retail media
A53: Roleplay 5 | C53: Construtora: compra x locação para stand temporário
A54: Roleplay 6 | C54: Agência de eventos: 'tenho fornecedor mais barato'

Sheet Técnicas
A1: Técnicas de storytelling e speech comercial
A2: Referência rápida. Cada técnica indica em que bloco do Roteiro Mestre ela entra.
A3: Técnica | B3: Onde usar | C3: Como aplicar | D3: Exemplo LedWave
A4: Golden Circle (Simon Sinek) | B4: Bloco 5 (propósito) | C4: Comece pelo PORQUÊ (o propósito do cliente), depois o COMO (a solução) e só então O QUÊ (o painel). | D4: 'Sua vitrine pode ser um vendedor 24h' antes de 'temos painel de alto brilho P3.9'.
A5: StoryBrand: o cliente é o herói | B5: Bloco 4 (LedWave) | C5: O cliente é o herói da história; a LedWave é o guia que tem empatia e autoridade. O guia nunca rouba a cena. | D5: 'Você quer que sua loja seja a escolhida da rua. Nós já ajudamos centenas de lojas a chegar lá.'
A6: Challenger Sale: ensinar algo novo | B6: Bloco 1 e 3 | C6: Traga um insight que o cliente não tinha sobre o próprio negócio e que muda a forma de ele ver o problema. | D6: '80% a 90% das vendas ainda acontecem na loja física. Sua loja é a sua maior mídia, e está desligada.'
A7: SPIN Selling | B7: Bloco 2 | C7: Perguntas de Situação, Problema, Implicação e Necessidade de solução. Quem pergunta conduz. | D7: 'Quanto custa cada troca de campanha?' (P) → 'E quantas campanhas você deixa de fazer por isso?' (I).
A8: Aversão à perda / custo da inação | B8: Bloco 3 | C8: As pessoas se mexem mais para não perder do que para ganhar. Mostre o que ele perde por ficar parado. | D8: 'Cada dia com vitrine parada é fluxo de calçada que passa reto.'
A9: Regra de 3 | B9: Blocos 4 e 6 | C9: O cérebro memoriza listas de três. Três provas, três argumentos, três números. | D9: Receita, experiência, operação.
A10: Antes x Depois (contraste) | B10: Blocos 2 e 5 | C10: Mostre o espaço do cliente como é hoje e como será. Imagem vale mais que argumento. | D10: Mockup da fachada do cliente com o painel.
A11: Analogia | B11: Bloco 5 | C11: Explique o novo com algo que o cliente já conhece. | D11: 'O painel é um imóvel que paga aluguel em inserções.'
A12: Frase de efeito + pausa | B12: Blocos 5 e 8 | C12: Uma frase curta, ritmada e repetível. Diga, pare 3 segundos, e deixe o silêncio trabalhar. | D12: 'Vitrine parada é vendedor dormindo.'
A13: Prova social específica | B13: Bloco 4 e 6 | C13: Case do mesmo nicho e porte vale mais que dez logos genéricos. | D13: 'Uma rede de farmácias como a sua fez X.'
A14: Inoculação de objeção | B14: Bloco 7 | C14: Traga a objeção antes do cliente. Quem antecipa demonstra domínio. | D14: 'Talvez você esteja pensando que é caro para uma loja só. Vamos fazer a conta.'
... A19: Um slide, uma ideia | B19: Toda a apresentação | C19: Máximo de uma ideia e 6 palavras de destaque por slide. O executivo é o protagonista, não o slide. | D19: Slides de imagem cheia com uma frase.

Sheet Banco de Ideias
A1: Banco de Ideias dos Gestores
A2: Uma linha por ideia. A linha 5 é um exemplo. Status 'Aprovada' = levar para a matriz Nichos na próxima reunião.
A4: Data | B4: Gestor | C4: Nicho | D4: Tipo de contribuição | E4: Ideia (texto pronto para usar) | F4: Onde usar no roteiro | G4: Testada com cliente? Resultado | H4: Status | I4: Votos do time | J4: Responsável por migrar | L4: Resumo
A5: 46314 | B5: Exemplo (apagar) | C5: Farmácias e Drogarias | D5: Gancho de abertura | E5: Se o seu cliente estivesse com dor de cabeça na esquina da sua farmácia, ele veria a sua loja antes da concorrente? | F5: 1. Abertura / Gancho | G5: Testado em 2 reuniões: gerou conversa sobre fachada | H5: Em teste em campo | I5: 3 | L5: Nova | M5: =COUNTIF($H$5:$H$305,L5) -> 0
L6: Em teste em campo | M6: =COUNTIF($H$5:$H$305,L6) -> 1
L7: Aprovada (levar à matriz) | M7: =COUNTIF($H$5:$H$305,L7) -> 0
L8: Descartada | M8: =COUNTIF($H$5:$H$305,L8) -> 0
L10: Total de ideias | M10: =COUNTA($E$5:$E$305) -> 1

Sheet Listas
A1: Nichos | B1: Tipos de contribuição | C1: Blocos do roteiro | D1: Status
A2: =IF(Nichos!A4="","",Nichos!A4) -> Varejo de Moda e Vitrines | B2: Gancho de abertura | C2: 1. Abertura / Gancho | D2: Nova
A3: =IF(Nichos!A5="","",Nichos!A5) -> Supermercados, Atacarejos e Home Centers | B3: Argumento | C3: 2. O mundo do cliente (dor) | D3: Em teste em campo
A4: =IF(Nichos!A6="","",Nichos!A6) -> Farmácias e Drogarias | B4: Frase de efeito | C4: 3. Custo da inação | D4: Aprovada (levar à matriz)
A5: =IF(Nichos!A7="","",Nichos!A7) -> Postos de Combustível e Conveniência | B5: Objeção + resposta | C5: 4. Quem é a LedWave (o guia) | D5: Descartada
A6: =IF(Nichos!A8="","",Nichos!A8) -> DOOH e Investidores de Mídia | B6: Case / prova | C6: 5. A virada: o porquê (propósito)
A7: =IF(Nichos!A9="","",Nichos!A9) -> Shopping Centers | B7: Pergunta de descoberta | C7: 6. Como funciona (3 argumentos)
A8: =IF(Nichos!A10="","",Nichos!A10) -> Concessionárias de Veículos | B8: História / analogia | C8: 7. Objeções antecipadas + números
A9: =IF(Nichos!A11="","",Nichos!A11) -> Construtoras e Stands de Vendas | B9: Técnica de apresentação | C9: 8. Fechamento e próximo passo
A10: =IF(Nichos!A12="","",Nichos!A12) -> Franquias e Redes
A11: =IF(Nichos!A13="","",Nichos!A13) -> Bares, Restaurantes e Food Service
A12: =IF(Nichos!A14="","",Nichos!A14) -> Igrejas e Centros Religiosos
A13: =IF(Nichos!A15="","",Nichos!A15) -> Hotéis, Parques, Clubes e Piscinas
A14: =IF(Nichos!A16="","",Nichos!A16) -> Eventos, Agências e Produtoras
A15: =IF(Nichos!A17="","",Nichos!A17) -> Corporativo (Comunicação Interna e Recepções)
A16: =IF(Nichos!A18="","",Nichos!A18) -> Educação (Escolas, Faculdades e Universidades)
A17: =IF(Nichos!A19="","",Nichos!A19) -> Saúde (Hospitais, Clínicas e Laboratórios)
A18: =IF(Nichos!A20="","",Nichos!A20) -> Arenas, Estádios, Academias e Esportes
A19: =IF(Nichos!A21="","",Nichos!A21) -> Poder Público e Mobiliário Urbano
A20: =IF(Nichos!A22="","",Nichos!A22)
A21: =IF(Nichos!A23="","",Nichos!A23)
... A60: =IF(Nichos!A62="","",Nichos!A62)
